<!-- SLIDE 21: 21_UC_KEY_CASES -->
<!-- RELS:
<?xml version="1.0" encoding="UTF-8" standalone="yes"?>
<Relationships xmlns="http://schemas.openxmlformats.org/package/2006/relationships"><Relationship Id="rId3" Type="http://schemas.openxmlformats.org/officeDocument/2006/relationships/image" Target="../media/image14.emf"/><Relationship Id="rId7" Type="http://schemas.openxmlformats.org/officeDocument/2006/relationships/slide" Target="slide25.xml"/><Relationship Id="rId2" Type="http://schemas.openxmlformats.org/officeDocument/2006/relationships/image" Target="../media/image12.png"/><Relationship Id="rId1" Type="http://schemas.openxmlformats.org/officeDocument/2006/relationships/slideLayout" Target="../slideLayouts/slideLayout33.xml"/><Relationship Id="rId6" Type="http://schemas.openxmlformats.org/officeDocument/2006/relationships/slide" Target="slide24.xml"/><Relationship Id="rId5" Type="http://schemas.openxmlformats.org/officeDocument/2006/relationships/slide" Target="slide23.xml"/><Relationship Id="rId4" Type="http://schemas.openxmlformats.org/officeDocument/2006/relationships/slide" Target="slide22.xml"/></Relationships>
-->
<?xml version="1.0" encoding="UTF-8" standalone="yes"?>
<p:sld xmlns:a="http://schemas.openxmlformats.org/drawingml/2006/main" xmlns:r="http://schemas.openxmlformats.org/officeDocument/2006/relationships" xmlns:p="http://schemas.openxmlformats.org/presentationml/2006/main"><p:cSld><p:spTree><p:nvGrpSpPr><p:cNvPr id="1" name=""><a:extLst><a:ext uri="{FF2B5EF4-FFF2-40B4-BE49-F238E27FC236}"><a16:creationId xmlns:a16="http://schemas.microsoft.com/office/drawing/2014/main" id="{700889CB-6B4F-C55C-6EFB-1DB512F1C343}"/></a:ext></a:extLst></p:cNvPr><p:cNvGrpSpPr/><p:nvPr/></p:nvGrpSpPr><p:grpSpPr><a:xfrm><a:off x="0" y="0"/><a:ext cx="0" cy="0"/><a:chOff x="0" y="0"/><a:chExt cx="0" cy="0"/></a:xfrm></p:grpSpPr><p:pic><p:nvPicPr><p:cNvPr id="1071" name="Picture 1070"><a:extLst><a:ext uri="{FF2B5EF4-FFF2-40B4-BE49-F238E27FC236}"><a16:creationId xmlns:a16="http://schemas.microsoft.com/office/drawing/2014/main" id="{51B809B8-A12E-59D6-54B1-052727634F17}"/></a:ext></a:extLst></p:cNvPr><p:cNvPicPr><a:picLocks noChangeAspect="1"/></p:cNvPicPr><p:nvPr/></p:nvPicPr><p:blipFill><a:blip r:embed="rId2"/><a:stretch><a:fillRect/></a:stretch></p:blipFill><p:spPr><a:xfrm><a:off x="30901" y="0"/><a:ext cx="12130199" cy="6858000"/></a:xfrm><a:prstGeom prst="rect"><a:avLst/></a:prstGeom></p:spPr></p:pic><p:sp><p:nvSpPr><p:cNvPr id="14" name="TextBox 13"><a:extLst><a:ext uri="{FF2B5EF4-FFF2-40B4-BE49-F238E27FC236}"><a16:creationId xmlns:a16="http://schemas.microsoft.com/office/drawing/2014/main" id="{89F98FE0-C36D-B8DF-7001-E5C2EE322C54}"/></a:ext></a:extLst></p:cNvPr><p:cNvSpPr txBox="1"/><p:nvPr/></p:nvSpPr><p:spPr><a:xfrm><a:off x="1092520" y="199527"/><a:ext cx="7145705" cy="687048"/></a:xfrm><a:prstGeom prst="rect"><a:avLst/></a:prstGeom><a:solidFill><a:schemeClr val="bg1"/></a:solidFill><a:effectLst/></p:spPr><p:txBody><a:bodyPr wrap="square" lIns="0" tIns="192024" rIns="137160" bIns="91440" rtlCol="0" anchor="t"><a:spAutoFit/></a:bodyPr><a:lstStyle><a:defPPr><a:defRPr lang="en-GB"/></a:defPPr><a:lvl1pPr marR="0" lvl="0" indent="0" fontAlgn="auto"><a:lnSpc><a:spcPct val="80000"/></a:lnSpc><a:spcBef><a:spcPts val="0"/></a:spcBef><a:spcAft><a:spcPts val="0"/></a:spcAft><a:buClrTx/><a:buSzTx/><a:buFontTx/><a:buNone/><a:tabLst/><a:defRPr kumimoji="0" sz="2800" b="1" i="0" u="none" strike="noStrike" cap="none" spc="0" normalizeH="0" baseline="0"><a:ln><a:noFill/></a:ln><a:solidFill><a:srgbClr val="ECBB69"/></a:solidFill><a:effectLst/><a:uLnTx/><a:uFillTx/><a:latin typeface="GT Walsheim Black"/></a:defRPr></a:lvl1pPr></a:lstStyle><a:p><a:pPr marL="0" marR="0" lvl="0" indent="0" algn="l" defTabSz="914400" rtl="0" eaLnBrk="1" fontAlgn="auto" latinLnBrk="0" hangingPunct="1"><a:lnSpc><a:spcPct val="80000"/></a:lnSpc><a:spcBef><a:spcPts val="0"/></a:spcBef><a:spcAft><a:spcPts val="0"/></a:spcAft><a:buClrTx/><a:buSzTx/><a:buFontTx/><a:buNone/><a:tabLst/><a:defRPr/></a:pPr><a:r><a:rPr kumimoji="0" lang="en-US" sz="3200" b="1" i="0" u="none" strike="noStrike" kern="1200" cap="none" spc="0" normalizeH="0" baseline="0" noProof="0" dirty="0"><a:ln><a:noFill/></a:ln><a:solidFill><a:srgbClr val="ECBB69"/></a:solidFill><a:effectLst/><a:uLnTx/><a:uFillTx/><a:latin typeface="GT Walsheim Black"/><a:ea typeface="+mn-ea"/><a:cs typeface="+mn-cs"/></a:rPr><a:t>PHTN.ai IntelliOps</a:t></a:r><a:r><a:rPr kumimoji="0" lang="en-US" sz="3200" b="1" i="0" u="none" strike="noStrike" kern="1200" cap="none" spc="0" normalizeH="0" baseline="0" noProof="0" dirty="0"><a:ln><a:noFill/></a:ln><a:solidFill><a:srgbClr val="000000"><a:lumMod val="75000"/><a:lumOff val="25000"/></a:srgbClr></a:solidFill><a:effectLst/><a:uLnTx/><a:uFillTx/><a:latin typeface="GT Walsheim Black"/><a:ea typeface="+mn-ea"/><a:cs typeface="+mn-cs"/></a:rPr><a:t>: key use cases</a:t></a:r></a:p></p:txBody></p:sp><p:pic><p:nvPicPr><p:cNvPr id="19" name="Picture 18"><a:extLst><a:ext uri="{FF2B5EF4-FFF2-40B4-BE49-F238E27FC236}"><a16:creationId xmlns:a16="http://schemas.microsoft.com/office/drawing/2014/main" id="{15E28C72-07C1-DE03-7AEB-8D1D21E55CA2}"/></a:ext></a:extLst></p:cNvPr><p:cNvPicPr><a:picLocks noChangeAspect="1"/></p:cNvPicPr><p:nvPr/></p:nvPicPr><p:blipFill><a:blip r:embed="rId3"/><a:srcRect r="29462" b="35780"/><a:stretch><a:fillRect/></a:stretch></p:blipFill><p:spPr><a:xfrm><a:off x="353257" y="310598"/><a:ext cx="612648" cy="557778"/></a:xfrm><a:prstGeom prst="rect"><a:avLst/></a:prstGeom></p:spPr></p:pic><p:graphicFrame><p:nvGraphicFramePr><p:cNvPr id="18" name="Table 17"><a:extLst><a:ext uri="{FF2B5EF4-FFF2-40B4-BE49-F238E27FC236}"><a16:creationId xmlns:a16="http://schemas.microsoft.com/office/drawing/2014/main" id="{75AE350A-3D41-14A6-26F6-261686D396F6}"/></a:ext></a:extLst></p:cNvPr><p:cNvGraphicFramePr><a:graphicFrameLocks noGrp="1"/></p:cNvGraphicFramePr><p:nvPr/></p:nvGraphicFramePr><p:xfrm><a:off x="353257" y="1570724"/><a:ext cx="11522034" cy="5127500"/></p:xfrm><a:graphic><a:graphicData uri="http://schemas.openxmlformats.org/drawingml/2006/table"><a:tbl><a:tblPr bandRow="1"><a:tableStyleId>{5C22544A-7EE6-4342-B048-85BDC9FD1C3A}</a:tableStyleId></a:tblPr><a:tblGrid><a:gridCol w="647163"><a:extLst><a:ext uri="{9D8B030D-6E8A-4147-A177-3AD203B41FA5}"><a16:colId xmlns:a16="http://schemas.microsoft.com/office/drawing/2014/main" val="381441800"/></a:ext></a:extLst></a:gridCol><a:gridCol w="1184193"><a:extLst><a:ext uri="{9D8B030D-6E8A-4147-A177-3AD203B41FA5}"><a16:colId xmlns:a16="http://schemas.microsoft.com/office/drawing/2014/main" val="1402619215"/></a:ext></a:extLst></a:gridCol><a:gridCol w="2499530"><a:extLst><a:ext uri="{9D8B030D-6E8A-4147-A177-3AD203B41FA5}"><a16:colId xmlns:a16="http://schemas.microsoft.com/office/drawing/2014/main" val="1831766779"/></a:ext></a:extLst></a:gridCol><a:gridCol w="1492370"><a:extLst><a:ext uri="{9D8B030D-6E8A-4147-A177-3AD203B41FA5}"><a16:colId xmlns:a16="http://schemas.microsoft.com/office/drawing/2014/main" val="2161338598"/></a:ext></a:extLst></a:gridCol><a:gridCol w="4244196"><a:extLst><a:ext uri="{9D8B030D-6E8A-4147-A177-3AD203B41FA5}"><a16:colId xmlns:a16="http://schemas.microsoft.com/office/drawing/2014/main" val="1062290496"/></a:ext></a:extLst></a:gridCol><a:gridCol w="1454582"><a:extLst><a:ext uri="{9D8B030D-6E8A-4147-A177-3AD203B41FA5}"><a16:colId xmlns:a16="http://schemas.microsoft.com/office/drawing/2014/main" val="1820030"/></a:ext></a:extLst></a:gridCol></a:tblGrid><a:tr h="263935"><a:tc><a:txBody><a:bodyPr/><a:lstStyle/><a:p><a:pPr algn="ctr" fontAlgn="base"><a:lnSpc><a:spcPts val="1425"/></a:lnSpc><a:buNone/></a:pPr><a:r><a:rPr lang="en-US" sz="1200"><a:solidFill><a:schemeClr val="bg1"/></a:solidFill><a:effectLst/><a:latin typeface="GT Walsheim Medium"/></a:rPr><a:t>#</a:t></a:r><a:endParaRPr lang="en-US"><a:solidFill><a:schemeClr val="bg1"/></a:solidFill><a:effectLst/><a:latin typeface="GT Walsheim Medium"/></a:endParaRPr></a:p></a:txBody><a:tcPr marL="45720" marR="45720" anchor="ctr"><a:lnL w="9525" cap="flat" cmpd="sng" algn="ctr"><a:noFill/><a:prstDash val="solid"/><a:round/><a:headEnd type="none" w="med" len="med"/><a:tailEnd type="none" w="med" len="med"/></a:lnL><a:lnR w="9525" cap="flat" cmpd="sng" algn="ctr"><a:noFill/><a:prstDash val="solid"/><a:round/><a:headEnd type="none" w="med" len="med"/><a:tailEnd type="none" w="med" len="med"/></a:lnR><a:lnT w="9525" cap="flat" cmpd="sng" algn="ctr"><a:noFill/><a:prstDash val="solid"/><a:round/><a:headEnd type="none" w="med" len="med"/><a:tailEnd type="none" w="med" len="med"/></a:lnT><a:lnB w="9525" cap="flat" cmpd="sng" algn="ctr"><a:noFill/><a:prstDash val="solid"/><a:round/><a:headEnd type="none" w="med" len="med"/><a:tailEnd type="none" w="med" len="med"/></a:lnB><a:lnTlToBr w="12700" cmpd="sng"><a:noFill/><a:prstDash val="solid"/></a:lnTlToBr><a:lnBlToTr w="12700" cmpd="sng"><a:noFill/><a:prstDash val="solid"/></a:lnBlToTr><a:solidFill><a:schemeClr val="tx1"><a:lumMod val="75000"/><a:lumOff val="25000"/></a:schemeClr></a:solidFill></a:tcPr></a:tc><a:tc><a:txBody><a:bodyPr/><a:lstStyle/><a:p><a:pPr lvl="0" algn="ctr"><a:lnSpc><a:spcPts val="1425"/></a:lnSpc><a:buNone/></a:pPr><a:r><a:rPr lang="en-US" sz="1200"><a:solidFill><a:schemeClr val="bg1"/></a:solidFill><a:effectLst/><a:latin typeface="GT Walsheim Medium"/></a:rPr><a:t>CATEGORY</a:t></a:r><a:endParaRPr lang="en-US"><a:solidFill><a:schemeClr val="bg1"/></a:solidFill></a:endParaRPr></a:p></a:txBody><a:tcPr marL="45720" marR="45720" anchor="ctr"><a:lnL w="9525" cap="flat" cmpd="sng" algn="ctr"><a:noFill/><a:prstDash val="solid"/><a:round/><a:headEnd type="none" w="med" len="med"/><a:tailEnd type="none" w="med" len="med"/></a:lnL><a:lnR w="9525" cap="flat" cmpd="sng" algn="ctr"><a:noFill/><a:prstDash val="solid"/><a:round/><a:headEnd type="none" w="med" len="med"/><a:tailEnd type="none" w="med" len="med"/></a:lnR><a:lnT w="9525" cap="flat" cmpd="sng" algn="ctr"><a:noFill/><a:prstDash val="solid"/><a:round/><a:headEnd type="none" w="med" len="med"/><a:tailEnd type="none" w="med" len="med"/></a:lnT><a:lnB w="9525" cap="flat" cmpd="sng" algn="ctr"><a:noFill/><a:prstDash val="solid"/><a:round/><a:headEnd type="none" w="med" len="med"/><a:tailEnd type="none" w="med" len="med"/></a:lnB><a:lnTlToBr w="12700" cmpd="sng"><a:noFill/><a:prstDash val="solid"/></a:lnTlToBr><a:lnBlToTr w="12700" cmpd="sng"><a:noFill/><a:prstDash val="solid"/></a:lnBlToTr><a:solidFill><a:schemeClr val="tx1"><a:lumMod val="75000"/><a:lumOff val="25000"/></a:schemeClr></a:solidFill></a:tcPr></a:tc><a:tc><a:txBody><a:bodyPr/><a:lstStyle/><a:p><a:pPr lvl="0" algn="ctr"><a:lnSpc><a:spcPts val="1425"/></a:lnSpc><a:buNone/></a:pPr><a:r><a:rPr lang="en-US" sz="1200"><a:solidFill><a:schemeClr val="bg1"/></a:solidFill><a:effectLst/><a:latin typeface="GT Walsheim Medium"/></a:rPr><a:t>USE CASE</a:t></a:r><a:endParaRPr lang="en-US"><a:solidFill><a:schemeClr val="bg1"/></a:solidFill></a:endParaRPr></a:p></a:txBody><a:tcPr marL="45720" marR="45720" anchor="ctr"><a:lnL w="9525" cap="flat" cmpd="sng" algn="ctr"><a:noFill/><a:prstDash val="solid"/><a:round/><a:headEnd type="none" w="med" len="med"/><a:tailEnd type="none" w="med" len="med"/></a:lnL><a:lnR w="9525" cap="flat" cmpd="sng" algn="ctr"><a:noFill/><a:prstDash val="solid"/><a:round/><a:headEnd type="none" w="med" len="med"/><a:tailEnd type="none" w="med" len="med"/></a:lnR><a:lnT w="9525" cap="flat" cmpd="sng" algn="ctr"><a:noFill/><a:prstDash val="solid"/><a:round/><a:headEnd type="none" w="med" len="med"/><a:tailEnd type="none" w="med" len="med"/></a:lnT><a:lnB w="9525" cap="flat" cmpd="sng" algn="ctr"><a:noFill/><a:prstDash val="solid"/><a:round/><a:headEnd type="none" w="med" len="med"/><a:tailEnd type="none" w="med" len="med"/></a:lnB><a:lnTlToBr w="12700" cmpd="sng"><a:noFill/><a:prstDash val="solid"/></a:lnTlToBr><a:lnBlToTr w="12700" cmpd="sng"><a:noFill/><a:prstDash val="solid"/></a:lnBlToTr><a:solidFill><a:schemeClr val="tx1"><a:lumMod val="75000"/><a:lumOff val="25000"/></a:schemeClr></a:solidFill></a:tcPr></a:tc><a:tc><a:txBody><a:bodyPr/><a:lstStyle/><a:p><a:pPr lvl="0" algn="ctr"><a:lnSpc><a:spcPts val="1425"/></a:lnSpc><a:buNone/></a:pPr><a:r><a:rPr lang="en-US" sz="1200"><a:solidFill><a:schemeClr val="bg1"/></a:solidFill><a:effectLst/><a:latin typeface="GT Walsheim Medium"/></a:rPr><a:t>SUPERAGENT</a:t></a:r></a:p></a:txBody><a:tcPr marL="45720" marR="45720" anchor="ctr"><a:lnL w="9525" cap="flat" cmpd="sng" algn="ctr"><a:noFill/><a:prstDash val="solid"/><a:round/><a:headEnd type="none" w="med" len="med"/><a:tailEnd type="none" w="med" len="med"/></a:lnL><a:lnR w="9524"><a:noFill/></a:lnR><a:lnT w="9524"><a:noFill/></a:lnT><a:lnB w="9524"><a:noFill/></a:lnB><a:lnTlToBr w="12700" cmpd="sng"><a:noFill/><a:prstDash val="solid"/></a:lnTlToBr><a:lnBlToTr w="12700" cmpd="sng"><a:noFill/><a:prstDash val="solid"/></a:lnBlToTr><a:solidFill><a:schemeClr val="tx1"><a:lumMod val="75000"/><a:lumOff val="25000"/></a:schemeClr></a:solidFill></a:tcPr></a:tc><a:tc><a:txBody><a:bodyPr/><a:lstStyle/><a:p><a:pPr lvl="0" algn="ctr"><a:lnSpc><a:spcPts val="1425"/></a:lnSpc><a:buNone/></a:pPr><a:r><a:rPr lang="en-US" sz="1200"><a:solidFill><a:schemeClr val="bg1"/></a:solidFill><a:effectLst/><a:latin typeface="GT Walsheim Medium"/></a:rPr><a:t>SUB AGENTS  (shared platform agents, reused across UCs)</a:t></a:r><a:endParaRPr lang="en-US"><a:solidFill><a:schemeClr val="bg1"/></a:solidFill></a:endParaRPr></a:p></a:txBody><a:tcPr marL="45720" marR="45720" anchor="ctr"><a:lnL w="9524" cap="flat" cmpd="sng" algn="ctr"><a:noFill/><a:prstDash val="solid"/><a:round/><a:headEnd type="none" w="med" len="med"/><a:tailEnd type="none" w="med" len="med"/></a:lnL><a:lnR w="9525" cap="flat" cmpd="sng" algn="ctr"><a:noFill/><a:prstDash val="solid"/><a:round/><a:headEnd type="none" w="med" len="med"/><a:tailEnd type="none" w="med" len="med"/></a:lnR><a:lnT w="9525" cap="flat" cmpd="sng" algn="ctr"><a:noFill/><a:prstDash val="solid"/><a:round/><a:headEnd type="none" w="med" len="med"/><a:tailEnd type="none" w="med" len="med"/></a:lnT><a:lnB w="9525" cap="flat" cmpd="sng" algn="ctr"><a:noFill/><a:prstDash val="solid"/><a:round/><a:headEnd type="none" w="med" len="med"/><a:tailEnd type="none" w="med" len="med"/></a:lnB><a:lnTlToBr w="12700" cmpd="sng"><a:noFill/><a:prstDash val="solid"/></a:lnTlToBr><a:lnBlToTr w="12700" cmpd="sng"><a:noFill/><a:prstDash val="solid"/></a:lnBlToTr><a:solidFill><a:schemeClr val="tx1"><a:lumMod val="75000"/><a:lumOff val="25000"/></a:schemeClr></a:solidFill></a:tcPr></a:tc><a:tc><a:txBody><a:bodyPr/><a:lstStyle/><a:p><a:pPr lvl="0" algn="ctr"><a:lnSpc><a:spcPts val="1425"/></a:lnSpc><a:buNone/></a:pPr><a:endParaRPr lang="en-US"><a:solidFill><a:schemeClr val="bg1"/></a:solidFill></a:endParaRPr></a:p></a:txBody><a:tcPr marL="45720" marR="45720" anchor="ctr"><a:lnL w="9524" cap="flat" cmpd="sng" algn="ctr"><a:noFill/><a:prstDash val="solid"/><a:round/><a:headEnd type="none" w="med" len="med"/><a:tailEnd type="none" w="med" len="med"/></a:lnL><a:lnR w="9525" cap="flat" cmpd="sng" algn="ctr"><a:noFill/><a:prstDash val="solid"/><a:round/><a:headEnd type="none" w="med" len="med"/><a:tailEnd type="none" w="med" len="med"/></a:lnR><a:lnT w="9525" cap="flat" cmpd="sng" algn="ctr"><a:noFill/><a:prstDash val="solid"/><a:round/><a:headEnd type="none" w="med" len="med"/><a:tailEnd type="none" w="med" len="med"/></a:lnT><a:lnB w="9525" cap="flat" cmpd="sng" algn="ctr"><a:noFill/><a:prstDash val="solid"/><a:round/><a:headEnd type="none" w="med" len="med"/><a:tailEnd type="none" w="med" len="med"/></a:lnB><a:lnTlToBr w="12700" cmpd="sng"><a:noFill/><a:prstDash val="solid"/></a:lnTlToBr><a:lnBlToTr w="12700" cmpd="sng"><a:noFill/><a:prstDash val="solid"/></a:lnBlToTr><a:solidFill><a:schemeClr val="tx1"><a:lumMod val="75000"/><a:lumOff val="25000"/></a:schemeClr></a:solidFill></a:tcPr></a:tc><a:extLst><a:ext uri="{0D108BD9-81ED-4DB2-BD59-A6C34878D82A}"><a16:rowId xmlns:a16="http://schemas.microsoft.com/office/drawing/2014/main" val="2197290824"/></a:ext></a:extLst></a:tr><a:tr h="1377678"><a:tc><a:txBody><a:bodyPr/><a:lstStyle/><a:p><a:pPr algn="ctr" fontAlgn="base"><a:lnSpc><a:spcPts val="1425"/></a:lnSpc><a:buNone/></a:pPr><a:r><a:rPr lang="en-US" sz="1100" kern="1200"><a:solidFill><a:schemeClr val="dk1"/></a:solidFill><a:effectLst/><a:latin typeface="+mn-lt"/><a:ea typeface="+mn-ea"/><a:cs typeface="+mn-cs"/></a:rPr><a:t>UC1</a:t></a:r></a:p></a:txBody><a:tcPr marL="45720" marR="45720" anchor="ctr"><a:lnL w="9525" cap="flat" cmpd="sng" algn="ctr"><a:noFill/><a:prstDash val="solid"/><a:round/><a:headEnd type="none" w="med" len="med"/><a:tailEnd type="none" w="med" len="med"/></a:lnL><a:lnR w="9525" cap="flat" cmpd="sng" algn="ctr"><a:noFill/><a:prstDash val="solid"/><a:round/><a:headEnd type="none" w="med" len="med"/><a:tailEnd type="none" w="med" len="med"/></a:lnR><a:lnT w="9525" cap="flat" cmpd="sng" algn="ctr"><a:noFill/><a:prstDash val="solid"/><a:round/><a:headEnd type="none" w="med" len="med"/><a:tailEnd type="none" w="med" len="med"/></a:lnT><a:lnB w="9525" cap="flat" cmpd="sng" algn="ctr"><a:noFill/><a:prstDash val="solid"/><a:round/><a:headEnd type="none" w="med" len="med"/><a:tailEnd type="none" w="med" len="med"/></a:lnB><a:lnTlToBr w="12700" cmpd="sng"><a:noFill/><a:prstDash val="solid"/></a:lnTlToBr><a:lnBlToTr w="12700" cmpd="sng"><a:noFill/><a:prstDash val="solid"/></a:lnBlToTr><a:solidFill><a:schemeClr val="bg1"/></a:solidFill></a:tcPr></a:tc><a:tc><a:txBody><a:bodyPr/><a:lstStyle/><a:p><a:pPr marL="0" lvl="0" indent="0" algn="ctr" defTabSz="914400" rtl="0" eaLnBrk="1" latinLnBrk="0" hangingPunct="1"><a:lnSpc><a:spcPts val="1425"/></a:lnSpc><a:buNone/></a:pPr><a:r><a:rPr lang="en-US" sz="1050" b="0" i="0" u="none" strike="noStrike" kern="1200" baseline="0" noProof="0"><a:solidFill><a:srgbClr val="000000"/></a:solidFill><a:effectLst/><a:latin typeface="+mn-lt"/><a:ea typeface="+mn-ea"/><a:cs typeface="+mn-cs"/></a:rPr><a:t>Synthetic Transaction Monitoring (STM)</a:t></a:r></a:p></a:txBody><a:tcPr marL="45720" marR="45720" anchor="ctr"><a:lnL w="9525" cap="flat" cmpd="sng" algn="ctr"><a:noFill/><a:prstDash val="solid"/><a:round/><a:headEnd type="none" w="med" len="med"/><a:tailEnd type="none" w="med" len="med"/></a:lnL><a:lnR w="9525" cap="flat" cmpd="sng" algn="ctr"><a:noFill/><a:prstDash val="solid"/><a:round/><a:headEnd type="none" w="med" len="med"/><a:tailEnd type="none" w="med" len="med"/></a:lnR><a:lnT w="9525" cap="flat" cmpd="sng" algn="ctr"><a:noFill/><a:prstDash val="solid"/><a:round/><a:headEnd type="none" w="med" len="med"/><a:tailEnd type="none" w="med" len="med"/></a:lnT><a:lnB w="9525" cap="flat" cmpd="sng" algn="ctr"><a:noFill/><a:prstDash val="solid"/><a:round/><a:headEnd type="none" w="med" len="med"/><a:tailEnd type="none" w="med" len="med"/></a:lnB><a:lnTlToBr w="12700" cmpd="sng"><a:noFill/><a:prstDash val="solid"/></a:lnTlToBr><a:lnBlToTr w="12700" cmpd="sng"><a:noFill/><a:prstDash val="solid"/></a:lnBlToTr><a:solidFill><a:schemeClr val="bg1"/></a:solidFill></a:tcPr></a:tc><a:tc><a:txBody><a:bodyPr/><a:lstStyle/><a:p><a:pPr marL="0" lvl="0" indent="0" algn="l"><a:buNone/></a:pPr><a:r><a:rPr lang="en-US" sz="1050" b="0" i="0" u="none" strike="noStrike" kern="1200" baseline="0" noProof="0"><a:solidFill><a:srgbClr val="000000"/></a:solidFill><a:effectLst/><a:latin typeface="+mn-lt"/><a:ea typeface="+mn-ea"/><a:cs typeface="+mn-cs"/></a:rPr><a:t>Synthetic monitoring-driven detection of critical customer journeys order flow, waitlist, reservation, menu browse, cart, checkout, payment reachability</a:t></a:r><a:endParaRPr lang="en-US" sz="1050" b="0" i="0" u="none" strike="noStrike" kern="1200" baseline="0"><a:solidFill><a:srgbClr val="000000"/></a:solidFill><a:effectLst/><a:latin typeface="+mn-lt"/><a:ea typeface="+mn-ea"/><a:cs typeface="+mn-cs"/></a:endParaRPr></a:p></a:txBody><a:tcPr marL="45720" marR="45720" anchor="ctr"><a:lnL w="9525" cap="flat" cmpd="sng" algn="ctr"><a:noFill/><a:prstDash val="solid"/><a:round/><a:headEnd type="none" w="med" len="med"/><a:tailEnd type="none" w="med" len="med"/></a:lnL><a:lnR w="9525" cap="flat" cmpd="sng" algn="ctr"><a:noFill/><a:prstDash val="solid"/><a:round/><a:headEnd type="none" w="med" len="med"/><a:tailEnd type="none" w="med" len="med"/></a:lnR><a:lnT w="9525" cap="flat" cmpd="sng" algn="ctr"><a:noFill/><a:prstDash val="solid"/><a:round/><a:headEnd type="none" w="med" len="med"/><a:tailEnd type="none" w="med" len="med"/></a:lnT><a:lnB w="9525" cap="flat" cmpd="sng" algn="ctr"><a:noFill/><a:prstDash val="solid"/><a:round/><a:headEnd type="none" w="med" len="med"/><a:tailEnd type="none" w="med" len="med"/></a:lnB><a:lnTlToBr w="12700" cmpd="sng"><a:noFill/><a:prstDash val="solid"/></a:lnTlToBr><a:lnBlToTr w="12700" cmpd="sng"><a:noFill/><a:prstDash val="solid"/></a:lnBlToTr><a:solidFill><a:schemeClr val="bg1"/></a:solidFill></a:tcPr></a:tc><a:tc><a:txBody><a:bodyPr/><a:lstStyle/><a:p><a:pPr marL="0" lvl="0" indent="0" algn="ctr" defTabSz="914400" rtl="0" eaLnBrk="1" latinLnBrk="0" hangingPunct="1"><a:lnSpc><a:spcPts val="1425"/></a:lnSpc><a:buNone/></a:pPr><a:r><a:rPr lang="en-US" sz="1050" b="0" i="0" u="none" strike="noStrike" kern="1200" noProof="0"><a:solidFill><a:schemeClr val="dk1"/></a:solidFill><a:effectLst/><a:latin typeface="+mn-lt"/><a:ea typeface="+mn-ea"/><a:cs typeface="+mn-cs"/></a:rPr><a:t>Journey Sentinel </a:t></a:r></a:p><a:p><a:pPr marL="0" lvl="0" indent="0" algn="ctr" defTabSz="914400" rtl="0" eaLnBrk="1" latinLnBrk="0" hangingPunct="1"><a:lnSpc><a:spcPts val="1425"/></a:lnSpc><a:buNone/></a:pPr><a:r><a:rPr lang="en-US" sz="1050" b="0" i="0" u="none" strike="noStrike" kern="1200" noProof="0"><a:solidFill><a:schemeClr val="dk1"/></a:solidFill><a:effectLst/><a:latin typeface="+mn-lt"/><a:ea typeface="+mn-ea"/><a:cs typeface="+mn-cs"/></a:rPr><a:t>Super Agent</a:t></a:r><a:endParaRPr lang="en-US" sz="1050" b="0" i="0" u="none" strike="noStrike" kern="1200"><a:solidFill><a:schemeClr val="dk1"/></a:solidFill><a:effectLst/><a:latin typeface="+mn-lt"/><a:ea typeface="+mn-ea"/><a:cs typeface="+mn-cs"/></a:endParaRPr></a:p></a:txBody><a:tcPr marL="45720" marR="45720" anchor="ctr"><a:lnL w="9525" cap="flat" cmpd="sng" algn="ctr"><a:noFill/><a:prstDash val="solid"/><a:round/><a:headEnd type="none" w="med" len="med"/><a:tailEnd type="none" w="med" len="med"/></a:lnL><a:lnR w="9524"><a:noFill/></a:lnR><a:lnT w="9524"><a:noFill/></a:lnT><a:lnB w="9524" cap="flat" cmpd="sng" algn="ctr"><a:noFill/><a:prstDash val="solid"/><a:round/><a:headEnd type="none" w="med" len="med"/><a:tailEnd type="none" w="med" len="med"/></a:lnB><a:lnTlToBr w="12700" cmpd="sng"><a:noFill/><a:prstDash val="solid"/></a:lnTlToBr><a:lnBlToTr w="12700" cmpd="sng"><a:noFill/><a:prstDash val="solid"/></a:lnBlToTr><a:solidFill><a:schemeClr val="bg1"/></a:solidFill></a:tcPr></a:tc><a:tc><a:txBody><a:bodyPr/><a:lstStyle/><a:p><a:pPr><a:lnSpc><a:spcPts val="1100"/></a:lnSpc></a:pPr><a:r><a:rPr sz="800" b="1" dirty="0"><a:solidFill><a:srgbClr val="383838"/></a:solidFill><a:latin typeface="GT Walsheim Bold"/></a:rPr><a:t>Journey Simulation Agent — </a:t></a:r><a:r><a:rPr sz="800" b="0" dirty="0"><a:solidFill><a:srgbClr val="484848"/></a:solidFill><a:latin typeface="GT Walsheim Light"/></a:rPr><a:t>synthetic user journey replay</a:t></a:r></a:p><a:p><a:pPr><a:lnSpc><a:spcPts val="1100"/></a:lnSpc></a:pPr><a:r><a:rPr sz="800" b="1" dirty="0"><a:solidFill><a:srgbClr val="383838"/></a:solidFill><a:latin typeface="GT Walsheim Bold"/></a:rPr><a:t>Endpoint Probe Agent — </a:t></a:r><a:r><a:rPr sz="800" b="0" dirty="0"><a:solidFill><a:srgbClr val="484848"/></a:solidFill><a:latin typeface="GT Walsheim Light"/></a:rPr><a:t>reachability &amp; latency checks</a:t></a:r></a:p><a:p><a:pPr><a:lnSpc><a:spcPts val="1100"/></a:lnSpc></a:pPr><a:r><a:rPr sz="800" b="1" dirty="0"><a:solidFill><a:srgbClr val="383838"/></a:solidFill><a:latin typeface="GT Walsheim Bold"/></a:rPr><a:t>Funnel Validation Agent — </a:t></a:r><a:r><a:rPr sz="800" b="0" dirty="0"><a:solidFill><a:srgbClr val="484848"/></a:solidFill><a:latin typeface="GT Walsheim Light"/></a:rPr><a:t>cart/checkout/payment step validation</a:t></a:r></a:p><a:p><a:pPr><a:lnSpc><a:spcPts val="1100"/></a:lnSpc></a:pPr><a:r><a:rPr sz="800" b="1" dirty="0"><a:solidFill><a:srgbClr val="383838"/></a:solidFill><a:latin typeface="GT Walsheim Bold"/></a:rPr><a:t>Early-Warning Agent — </a:t></a:r><a:r><a:rPr sz="800" b="0" dirty="0"><a:solidFill><a:srgbClr val="484848"/></a:solidFill><a:latin typeface="GT Walsheim Light"/></a:rPr><a:t>deviation alerts before customer impact</a:t></a:r></a:p><a:p><a:pPr><a:lnSpc><a:spcPts val="1100"/></a:lnSpc></a:pPr><a:r><a:rPr sz="800" b="1" dirty="0"><a:solidFill><a:srgbClr val="5BA4AF"/></a:solidFill><a:latin typeface="GT Walsheim Bold"/></a:rPr><a:t>Knowledge Lookup Agent — </a:t></a:r><a:r><a:rPr sz="800" b="0" dirty="0"><a:solidFill><a:srgbClr val="484848"/></a:solidFill><a:latin typeface="GT Walsheim Light"/></a:rPr><a:t>KB, Remedy history &amp; runbook search</a:t></a:r></a:p><a:p><a:pPr><a:lnSpc><a:spcPts val="1100"/></a:lnSpc></a:pPr><a:r><a:rPr sz="800" b="1" dirty="0"><a:solidFill><a:srgbClr val="5BA4AF"/></a:solidFill><a:latin typeface="GT Walsheim Bold"/></a:rPr><a:t>Scoring Agent — </a:t></a:r><a:r><a:rPr sz="800" b="0" dirty="0"><a:solidFill><a:srgbClr val="484848"/></a:solidFill><a:latin typeface="GT Walsheim Light"/></a:rPr><a:t>priority, severity &amp; business impact</a:t></a:r></a:p><a:p><a:pPr><a:lnSpc><a:spcPts val="1100"/></a:lnSpc></a:pPr><a:r><a:rPr sz="800" b="1" dirty="0"><a:solidFill><a:srgbClr val="5BA4AF"/></a:solidFill><a:latin typeface="GT Walsheim Bold"/></a:rPr><a:t>RCA Agent — </a:t></a:r><a:r><a:rPr sz="800" b="0" dirty="0"><a:solidFill><a:srgbClr val="484848"/></a:solidFill><a:latin typeface="GT Walsheim Light"/></a:rPr><a:t>root cause analysis generation</a:t></a:r></a:p><a:p><a:pPr><a:lnSpc><a:spcPts val="1100"/></a:lnSpc></a:pPr><a:r><a:rPr sz="800" b="1" dirty="0"><a:solidFill><a:srgbClr val="5BA4AF"/></a:solidFill><a:latin typeface="GT Walsheim Bold"/></a:rPr><a:t>Ticket Agent — </a:t></a:r><a:r><a:rPr sz="800" b="0" dirty="0"><a:solidFill><a:srgbClr val="484848"/></a:solidFill><a:latin typeface="GT Walsheim Light"/></a:rPr><a:t>Remedy ticket creation &amp; update</a:t></a:r></a:p><a:p><a:pPr><a:lnSpc><a:spcPts val="1100"/></a:lnSpc></a:pPr><a:r><a:rPr sz="800" b="1" dirty="0"><a:solidFill><a:srgbClr val="5BA4AF"/></a:solidFill><a:latin typeface="GT Walsheim Bold"/></a:rPr><a:t>Knowledge Agent — </a:t></a:r><a:r><a:rPr sz="800" b="0" dirty="0"><a:solidFill><a:srgbClr val="484848"/></a:solidFill><a:latin typeface="GT Walsheim Light"/></a:rPr><a:t>KB update &amp; continuous learning</a:t></a:r></a:p><a:p><a:pPr><a:lnSpc><a:spcPts val="1100"/></a:lnSpc></a:pPr><a:r><a:rPr sz="800" b="1" kern="1200" dirty="0"><a:solidFill><a:srgbClr val="5BA4AF"/></a:solidFill><a:latin typeface="GT Walsheim Bold"/><a:ea typeface="+mn-ea"/><a:cs typeface="+mn-cs"/></a:rPr><a:t>Notification Agent </a:t></a:r><a:r><a:rPr sz="800" b="1" kern="1200" dirty="0"><a:solidFill><a:srgbClr val="383838"/></a:solidFill><a:latin typeface="GT Walsheim Bold"/><a:ea typeface="+mn-ea"/><a:cs typeface="+mn-cs"/></a:rPr><a:t>— </a:t></a:r><a:r><a:rPr sz="800" b="0" dirty="0"><a:solidFill><a:srgbClr val="484848"/></a:solidFill><a:latin typeface="GT Walsheim Light"/></a:rPr><a:t>Teams, email &amp; xMatters escalation</a:t></a:r></a:p></a:txBody><a:tcPr marL="45720" marR="45720" anchor="ctr"><a:lnL w="9524" cap="flat" cmpd="sng" algn="ctr"><a:noFill/><a:prstDash val="solid"/><a:round/><a:headEnd type="none" w="med" len="med"/><a:tailEnd type="none" w="med" len="med"/></a:lnL><a:lnR w="9524" cap="flat" cmpd="sng" algn="ctr"><a:noFill/><a:prstDash val="solid"/><a:round/><a:headEnd type="none" w="med" len="med"/><a:tailEnd type="none" w="med" len="med"/></a:lnR><a:lnT w="9525" cap="flat" cmpd="sng" algn="ctr"><a:noFill/><a:prstDash val="solid"/><a:round/><a:headEnd type="none" w="med" len="med"/><a:tailEnd type="none" w="med" len="med"/></a:lnT><a:lnB w="9525" cap="flat" cmpd="sng" algn="ctr"><a:noFill/><a:prstDash val="solid"/><a:round/><a:headEnd type="none" w="med" len="med"/><a:tailEnd type="none" w="med" len="med"/></a:lnB><a:lnTlToBr w="12700" cmpd="sng"><a:noFill/><a:prstDash val="solid"/></a:lnTlToBr><a:lnBlToTr w="12700" cmpd="sng"><a:noFill/><a:prstDash val="solid"/></a:lnBlToTr><a:solidFill><a:schemeClr val="bg1"/></a:solidFill></a:tcPr></a:tc><a:tc><a:txBody><a:bodyPr/><a:lstStyle/><a:p><a:endParaRPr sz="800" b="0"><a:solidFill><a:srgbClr val="484848"/></a:solidFill><a:latin typeface="GT Walsheim Light"/></a:endParaRPr></a:p></a:txBody><a:tcPr marL="45720" marR="45720" anchor="ctr"><a:lnL w="9524" cap="flat" cmpd="sng" algn="ctr"><a:noFill/><a:prstDash val="solid"/><a:round/><a:headEnd type="none" w="med" len="med"/><a:tailEnd type="none" w="med" len="med"/></a:lnL><a:lnR w="9525" cap="flat" cmpd="sng" algn="ctr"><a:noFill/><a:prstDash val="solid"/><a:round/><a:headEnd type="none" w="med" len="med"/><a:tailEnd type="none" w="med" len="med"/></a:lnR><a:lnT w="9525" cap="flat" cmpd="sng" algn="ctr"><a:noFill/><a:prstDash val="solid"/><a:round/><a:headEnd type="none" w="med" len="med"/><a:tailEnd type="none" w="med" len="med"/></a:lnT><a:lnB w="9525" cap="flat" cmpd="sng" algn="ctr"><a:noFill/><a:prstDash val="solid"/><a:round/><a:headEnd type="none" w="med" len="med"/><a:tailEnd type="none" w="med" len="med"/></a:lnB><a:lnTlToBr w="12700" cmpd="sng"><a:noFill/><a:prstDash val="solid"/></a:lnTlToBr><a:lnBlToTr w="12700" cmpd="sng"><a:noFill/><a:prstDash val="solid"/></a:lnBlToTr><a:solidFill><a:schemeClr val="bg1"/></a:solidFill></a:tcPr></a:tc><a:extLst><a:ext uri="{0D108BD9-81ED-4DB2-BD59-A6C34878D82A}"><a16:rowId xmlns:a16="http://schemas.microsoft.com/office/drawing/2014/main" val="488498483"/></a:ext></a:extLst></a:tr><a:tr h="1174287"><a:tc><a:txBody><a:bodyPr/><a:lstStyle/><a:p><a:pPr algn="ctr" fontAlgn="base"><a:lnSpc><a:spcPts val="1425"/></a:lnSpc><a:buNone/></a:pPr><a:r><a:rPr lang="en-US" sz="1100"><a:effectLst/><a:latin typeface="+mn-lt"/></a:rPr><a:t>UC2</a:t></a:r><a:endParaRPr lang="en-US" sz="1600"><a:effectLst/><a:latin typeface="+mn-lt"/></a:endParaRPr></a:p></a:txBody><a:tcPr marL="45720" marR="45720" anchor="ctr"><a:lnL w="9525" cap="flat" cmpd="sng" algn="ctr"><a:noFill/><a:prstDash val="solid"/><a:round/><a:headEnd type="none" w="med" len="med"/><a:tailEnd type="none" w="med" len="med"/></a:lnL><a:lnR w="9525" cap="flat" cmpd="sng" algn="ctr"><a:noFill/><a:prstDash val="solid"/><a:round/><a:headEnd type="none" w="med" len="med"/><a:tailEnd type="none" w="med" len="med"/></a:lnR><a:lnT w="9525" cap="flat" cmpd="sng" algn="ctr"><a:noFill/><a:prstDash val="solid"/><a:round/><a:headEnd type="none" w="med" len="med"/><a:tailEnd type="none" w="med" len="med"/></a:lnT><a:lnB w="9525" cap="flat" cmpd="sng" algn="ctr"><a:noFill/><a:prstDash val="solid"/><a:round/><a:headEnd type="none" w="med" len="med"/><a:tailEnd type="none" w="med" len="med"/></a:lnB><a:lnTlToBr w="12700" cmpd="sng"><a:noFill/><a:prstDash val="solid"/></a:lnTlToBr><a:lnBlToTr w="12700" cmpd="sng"><a:noFill/><a:prstDash val="solid"/></a:lnBlToTr><a:solidFill><a:srgbClr val="E8F5F7"/></a:solidFill></a:tcPr></a:tc><a:tc><a:txBody><a:bodyPr/><a:lstStyle/><a:p><a:pPr marL="0" lvl="0" indent="0" algn="ctr"><a:buNone/></a:pPr><a:r><a:rPr lang="en-US" sz="1050" b="0" i="0" u="none" strike="noStrike" baseline="0" noProof="0"><a:solidFill><a:srgbClr val="000000"/></a:solidFill><a:effectLst/><a:latin typeface="+mn-lt"/></a:rPr><a:t>AI-Assisted Incident Triage &amp; Enrichment</a:t></a:r></a:p></a:txBody><a:tcPr marL="45720" marR="45720" anchor="ctr"><a:lnL w="9525" cap="flat" cmpd="sng" algn="ctr"><a:noFill/><a:prstDash val="solid"/><a:round/><a:headEnd type="none" w="med" len="med"/><a:tailEnd type="none" w="med" len="med"/></a:lnL><a:lnR w="9525" cap="flat" cmpd="sng" algn="ctr"><a:noFill/><a:prstDash val="solid"/><a:round/><a:headEnd type="none" w="med" len="med"/><a:tailEnd type="none" w="med" len="med"/></a:lnR><a:lnT w="9525" cap="flat" cmpd="sng" algn="ctr"><a:noFill/><a:prstDash val="solid"/><a:round/><a:headEnd type="none" w="med" len="med"/><a:tailEnd type="none" w="med" len="med"/></a:lnT><a:lnB w="9525" cap="flat" cmpd="sng" algn="ctr"><a:noFill/><a:prstDash val="solid"/><a:round/><a:headEnd type="none" w="med" len="med"/><a:tailEnd type="none" w="med" len="med"/></a:lnB><a:lnTlToBr w="12700" cmpd="sng"><a:noFill/><a:prstDash val="solid"/></a:lnTlToBr><a:lnBlToTr w="12700" cmpd="sng"><a:noFill/><a:prstDash val="solid"/></a:lnBlToTr><a:solidFill><a:srgbClr val="E8F5F7"/></a:solidFill></a:tcPr></a:tc><a:tc><a:txBody><a:bodyPr/><a:lstStyle/><a:p><a:pPr algn="l" fontAlgn="t"><a:buNone/></a:pPr><a:r><a:rPr lang="en-US" sz="1050" b="0" i="0" u="none" strike="noStrike" kern="1200" baseline="0"><a:solidFill><a:srgbClr val="000000"/></a:solidFill><a:effectLst/><a:latin typeface="+mn-lt"/><a:ea typeface="+mn-ea"/><a:cs typeface="+mn-cs"/></a:rPr><a:t>Incident-triggered AI support ticket reading, key-detail extraction, faster triage for store/order/payment failures and customer-reported errors</a:t></a:r></a:p></a:txBody><a:tcPr marL="76200" marR="76200" marT="76200" marB="76200" anchor="ctr"><a:lnL w="9525" cap="flat" cmpd="sng" algn="ctr"><a:noFill/><a:prstDash val="solid"/><a:round/><a:headEnd type="none" w="med" len="med"/><a:tailEnd type="none" w="med" len="med"/></a:lnL><a:lnR w="9525" cap="flat" cmpd="sng" algn="ctr"><a:noFill/><a:prstDash val="solid"/><a:round/><a:headEnd type="none" w="med" len="med"/><a:tailEnd type="none" w="med" len="med"/></a:lnR><a:lnT w="9525" cap="flat" cmpd="sng" algn="ctr"><a:noFill/><a:prstDash val="solid"/><a:round/><a:headEnd type="none" w="med" len="med"/><a:tailEnd type="none" w="med" len="med"/></a:lnT><a:lnB w="9525" cap="flat" cmpd="sng" algn="ctr"><a:noFill/><a:prstDash val="solid"/><a:round/><a:headEnd type="none" w="med" len="med"/><a:tailEnd type="none" w="med" len="med"/></a:lnB><a:lnTlToBr w="12700" cmpd="sng"><a:noFill/><a:prstDash val="solid"/></a:lnTlToBr><a:lnBlToTr w="12700" cmpd="sng"><a:noFill/><a:prstDash val="solid"/></a:lnBlToTr><a:solidFill><a:srgbClr val="E8F5F7"/></a:solidFill></a:tcPr></a:tc><a:tc><a:txBody><a:bodyPr/><a:lstStyle/><a:p><a:pPr algn="ctr" fontAlgn="t"><a:buNone/></a:pPr><a:r><a:rPr lang="en-US" sz="1050" b="0" i="0" u="none" strike="noStrike" kern="1200" baseline="0"><a:solidFill><a:srgbClr val="000000"/></a:solidFill><a:effectLst/><a:latin typeface="+mn-lt"/><a:ea typeface="+mn-ea"/><a:cs typeface="+mn-cs"/></a:rPr><a:t>Incident Triage </a:t></a:r></a:p><a:p><a:pPr algn="ctr" fontAlgn="t"><a:buNone/></a:pPr><a:r><a:rPr lang="en-US" sz="1050" b="0" i="0" u="none" strike="noStrike" kern="1200" baseline="0"><a:solidFill><a:srgbClr val="000000"/></a:solidFill><a:effectLst/><a:latin typeface="+mn-lt"/><a:ea typeface="+mn-ea"/><a:cs typeface="+mn-cs"/></a:rPr><a:t>Super Agent</a:t></a:r></a:p></a:txBody><a:tcPr marL="76200" marR="76200" marT="76200" marB="76200" anchor="ctr"><a:lnL w="9525" cap="flat" cmpd="sng" algn="ctr"><a:noFill/><a:prstDash val="solid"/><a:round/><a:headEnd type="none" w="med" len="med"/><a:tailEnd type="none" w="med" len="med"/></a:lnL><a:lnR w="9524"><a:noFill/></a:lnR><a:lnT w="9524"><a:noFill/></a:lnT><a:lnB w="9524" cap="flat" cmpd="sng" algn="ctr"><a:noFill/><a:prstDash val="solid"/><a:round/><a:headEnd type="none" w="med" len="med"/><a:tailEnd type="none" w="med" len="med"/></a:lnB><a:lnTlToBr w="12700" cmpd="sng"><a:noFill/><a:prstDash val="solid"/></a:lnTlToBr><a:lnBlToTr w="12700" cmpd="sng"><a:noFill/><a:prstDash val="solid"/></a:lnBlToTr><a:solidFill><a:srgbClr val="E8F5F7"/></a:solidFill></a:tcPr></a:tc><a:tc><a:txBody><a:bodyPr/><a:lstStyle/><a:p><a:pPr><a:lnSpc><a:spcPts val="1100"/></a:lnSpc></a:pPr><a:r><a:rPr sz="800" b="1"><a:solidFill><a:srgbClr val="383838"/></a:solidFill><a:latin typeface="GT Walsheim Bold"/></a:rPr><a:t>Ticket Ingestion Agent — </a:t></a:r><a:r><a:rPr sz="800" b="0"><a:solidFill><a:srgbClr val="484848"/></a:solidFill><a:latin typeface="GT Walsheim Light"/></a:rPr><a:t>Remedy / ServiceNow / Zendesk intake</a:t></a:r></a:p><a:p><a:pPr><a:lnSpc><a:spcPts val="1100"/></a:lnSpc></a:pPr><a:r><a:rPr sz="800" b="1"><a:solidFill><a:srgbClr val="383838"/></a:solidFill><a:latin typeface="GT Walsheim Bold"/></a:rPr><a:t>NLP Extraction Agent — </a:t></a:r><a:r><a:rPr sz="800" b="0"><a:solidFill><a:srgbClr val="484848"/></a:solidFill><a:latin typeface="GT Walsheim Light"/></a:rPr><a:t>intent, entity, severity extraction</a:t></a:r></a:p><a:p><a:pPr><a:lnSpc><a:spcPts val="1100"/></a:lnSpc></a:pPr><a:r><a:rPr sz="800" b="1"><a:solidFill><a:srgbClr val="5BA4AF"/></a:solidFill><a:latin typeface="GT Walsheim Bold"/></a:rPr><a:t>Knowledge Lookup Agent — </a:t></a:r><a:r><a:rPr sz="800" b="0"><a:solidFill><a:srgbClr val="484848"/></a:solidFill><a:latin typeface="GT Walsheim Light"/></a:rPr><a:t>KB, Remedy history &amp; runbook search</a:t></a:r></a:p><a:p><a:pPr><a:lnSpc><a:spcPts val="1100"/></a:lnSpc></a:pPr><a:r><a:rPr sz="800" b="1"><a:solidFill><a:srgbClr val="383838"/></a:solidFill><a:latin typeface="GT Walsheim Bold"/></a:rPr><a:t>Triage Recommendation Agent — </a:t></a:r><a:r><a:rPr sz="800" b="0"><a:solidFill><a:srgbClr val="484848"/></a:solidFill><a:latin typeface="GT Walsheim Light"/></a:rPr><a:t>priority, assignment, next action</a:t></a:r></a:p><a:p><a:pPr><a:lnSpc><a:spcPts val="1100"/></a:lnSpc></a:pPr><a:r><a:rPr sz="800" b="1"><a:solidFill><a:srgbClr val="5BA4AF"/></a:solidFill><a:latin typeface="GT Walsheim Bold"/></a:rPr><a:t>RCA Agent — </a:t></a:r><a:r><a:rPr sz="800" b="0"><a:solidFill><a:srgbClr val="484848"/></a:solidFill><a:latin typeface="GT Walsheim Light"/></a:rPr><a:t>root cause analysis generation</a:t></a:r></a:p><a:p><a:pPr><a:lnSpc><a:spcPts val="1100"/></a:lnSpc></a:pPr><a:r><a:rPr sz="800" b="1"><a:solidFill><a:srgbClr val="5BA4AF"/></a:solidFill><a:latin typeface="GT Walsheim Bold"/></a:rPr><a:t>Ticket Agent — </a:t></a:r><a:r><a:rPr sz="800" b="0"><a:solidFill><a:srgbClr val="484848"/></a:solidFill><a:latin typeface="GT Walsheim Light"/></a:rPr><a:t>Remedy ticket update</a:t></a:r></a:p><a:p><a:pPr><a:lnSpc><a:spcPts val="1100"/></a:lnSpc></a:pPr><a:r><a:rPr sz="800" b="1"><a:solidFill><a:srgbClr val="5BA4AF"/></a:solidFill><a:latin typeface="GT Walsheim Bold"/></a:rPr><a:t>Knowledge Agent — </a:t></a:r><a:r><a:rPr sz="800" b="0"><a:solidFill><a:srgbClr val="484848"/></a:solidFill><a:latin typeface="GT Walsheim Light"/></a:rPr><a:t>KB update &amp; continuous learning</a:t></a:r></a:p><a:p><a:pPr><a:lnSpc><a:spcPts val="1100"/></a:lnSpc></a:pPr><a:r><a:rPr sz="800" b="1"><a:solidFill><a:srgbClr val="5BA4AF"/></a:solidFill><a:latin typeface="GT Walsheim Bold"/></a:rPr><a:t>Notification Agent — </a:t></a:r><a:r><a:rPr sz="800" b="0"><a:solidFill><a:srgbClr val="484848"/></a:solidFill><a:latin typeface="GT Walsheim Light"/></a:rPr><a:t>Teams, email &amp; xMatters escalation</a:t></a:r></a:p></a:txBody><a:tcPr marL="76200" marR="76200" marT="76200" marB="76200" anchor="ctr"><a:lnL w="9524" cap="flat" cmpd="sng" algn="ctr"><a:noFill/><a:prstDash val="solid"/><a:round/><a:headEnd type="none" w="med" len="med"/><a:tailEnd type="none" w="med" len="med"/></a:lnL><a:lnR w="9524" cap="flat" cmpd="sng" algn="ctr"><a:noFill/><a:prstDash val="solid"/><a:round/><a:headEnd type="none" w="med" len="med"/><a:tailEnd type="none" w="med" len="med"/></a:lnR><a:lnT w="9525" cap="flat" cmpd="sng" algn="ctr"><a:noFill/><a:prstDash val="solid"/><a:round/><a:headEnd type="none" w="med" len="med"/><a:tailEnd type="none" w="med" len="med"/></a:lnT><a:lnB w="9525" cap="flat" cmpd="sng" algn="ctr"><a:noFill/><a:prstDash val="solid"/><a:round/><a:headEnd type="none" w="med" len="med"/><a:tailEnd type="none" w="med" len="med"/></a:lnB><a:lnTlToBr w="12700" cmpd="sng"><a:noFill/><a:prstDash val="solid"/></a:lnTlToBr><a:lnBlToTr w="12700" cmpd="sng"><a:noFill/><a:prstDash val="solid"/></a:lnBlToTr><a:solidFill><a:srgbClr val="E8F5F7"/></a:solidFill></a:tcPr></a:tc><a:tc><a:txBody><a:bodyPr/><a:lstStyle/><a:p><a:endParaRPr sz="800" b="0"><a:solidFill><a:srgbClr val="484848"/></a:solidFill><a:latin typeface="GT Walsheim Light"/></a:endParaRPr></a:p></a:txBody><a:tcPr marL="76200" marR="76200" marT="76200" marB="76200" anchor="ctr"><a:lnL w="9524" cap="flat" cmpd="sng" algn="ctr"><a:noFill/><a:prstDash val="solid"/><a:round/><a:headEnd type="none" w="med" len="med"/><a:tailEnd type="none" w="med" len="med"/></a:lnL><a:lnR w="9525" cap="flat" cmpd="sng" algn="ctr"><a:noFill/><a:prstDash val="solid"/><a:round/><a:headEnd type="none" w="med" len="med"/><a:tailEnd type="none" w="med" len="med"/></a:lnR><a:lnT w="9525" cap="flat" cmpd="sng" algn="ctr"><a:noFill/><a:prstDash val="solid"/><a:round/><a:headEnd type="none" w="med" len="med"/><a:tailEnd type="none" w="med" len="med"/></a:lnT><a:lnB w="9525" cap="flat" cmpd="sng" algn="ctr"><a:noFill/><a:prstDash val="solid"/><a:round/><a:headEnd type="none" w="med" len="med"/><a:tailEnd type="none" w="med" len="med"/></a:lnB><a:lnTlToBr w="12700" cmpd="sng"><a:noFill/><a:prstDash val="solid"/></a:lnTlToBr><a:lnBlToTr w="12700" cmpd="sng"><a:noFill/><a:prstDash val="solid"/></a:lnBlToTr><a:solidFill><a:srgbClr val="E8F5F7"/></a:solidFill></a:tcPr></a:tc><a:extLst><a:ext uri="{0D108BD9-81ED-4DB2-BD59-A6C34878D82A}"><a16:rowId xmlns:a16="http://schemas.microsoft.com/office/drawing/2014/main" val="2769295995"/></a:ext></a:extLst></a:tr><a:tr h="1304363"><a:tc><a:txBody><a:bodyPr/><a:lstStyle/><a:p><a:pPr lvl="0" algn="ctr"><a:lnSpc><a:spcPts val="1425"/></a:lnSpc><a:buNone/></a:pPr><a:r><a:rPr lang="en-US" sz="1100"><a:effectLst/><a:latin typeface="+mn-lt"/></a:rPr><a:t>UC3</a:t></a:r><a:endParaRPr lang="en-US" sz="1600"><a:effectLst/><a:latin typeface="+mn-lt"/></a:endParaRPr></a:p></a:txBody><a:tcPr marL="45720" marR="45720" anchor="ctr"><a:lnL w="9525" cap="flat" cmpd="sng" algn="ctr"><a:noFill/><a:prstDash val="solid"/><a:round/><a:headEnd type="none" w="med" len="med"/><a:tailEnd type="none" w="med" len="med"/></a:lnL><a:lnR w="9525" cap="flat" cmpd="sng" algn="ctr"><a:noFill/><a:prstDash val="solid"/><a:round/><a:headEnd type="none" w="med" len="med"/><a:tailEnd type="none" w="med" len="med"/></a:lnR><a:lnT w="9525" cap="flat" cmpd="sng" algn="ctr"><a:noFill/><a:prstDash val="solid"/><a:round/><a:headEnd type="none" w="med" len="med"/><a:tailEnd type="none" w="med" len="med"/></a:lnT><a:lnB w="9525" cap="flat" cmpd="sng" algn="ctr"><a:noFill/><a:prstDash val="solid"/><a:round/><a:headEnd type="none" w="med" len="med"/><a:tailEnd type="none" w="med" len="med"/></a:lnB><a:lnTlToBr w="12700" cmpd="sng"><a:noFill/><a:prstDash val="solid"/></a:lnTlToBr><a:lnBlToTr w="12700" cmpd="sng"><a:noFill/><a:prstDash val="solid"/></a:lnBlToTr><a:noFill/></a:tcPr></a:tc><a:tc><a:txBody><a:bodyPr/><a:lstStyle/><a:p><a:pPr marL="0" lvl="0" indent="0" algn="ctr"><a:buNone/></a:pPr><a:r><a:rPr lang="en-US" sz="1050" b="0" i="0" u="none" strike="noStrike" baseline="0" noProof="0"><a:solidFill><a:srgbClr val="000000"/></a:solidFill><a:effectLst/><a:latin typeface="+mn-lt"/></a:rPr><a:t>Observability &amp; Anomaly Detection</a:t></a:r></a:p></a:txBody><a:tcPr marL="45720" marR="45720" anchor="ctr"><a:lnL w="9525" cap="flat" cmpd="sng" algn="ctr"><a:noFill/><a:prstDash val="solid"/><a:round/><a:headEnd type="none" w="med" len="med"/><a:tailEnd type="none" w="med" len="med"/></a:lnL><a:lnR w="9525" cap="flat" cmpd="sng" algn="ctr"><a:noFill/><a:prstDash val="solid"/><a:round/><a:headEnd type="none" w="med" len="med"/><a:tailEnd type="none" w="med" len="med"/></a:lnR><a:lnT w="9525" cap="flat" cmpd="sng" algn="ctr"><a:noFill/><a:prstDash val="solid"/><a:round/><a:headEnd type="none" w="med" len="med"/><a:tailEnd type="none" w="med" len="med"/></a:lnT><a:lnB w="9525" cap="flat" cmpd="sng" algn="ctr"><a:noFill/><a:prstDash val="solid"/><a:round/><a:headEnd type="none" w="med" len="med"/><a:tailEnd type="none" w="med" len="med"/></a:lnB><a:lnTlToBr w="12700" cmpd="sng"><a:noFill/><a:prstDash val="solid"/></a:lnTlToBr><a:lnBlToTr w="12700" cmpd="sng"><a:noFill/><a:prstDash val="solid"/></a:lnBlToTr><a:noFill/></a:tcPr></a:tc><a:tc><a:txBody><a:bodyPr/><a:lstStyle/><a:p><a:pPr algn="l" fontAlgn="t"><a:buNone/></a:pPr><a:r><a:rPr lang="en-US" sz="1050" b="0" i="0" u="none" strike="noStrike" kern="1200" baseline="0"><a:solidFill><a:srgbClr val="000000"/></a:solidFill><a:effectLst/><a:latin typeface="+mn-lt"/><a:ea typeface="+mn-ea"/><a:cs typeface="+mn-cs"/></a:rPr><a:t>Continuous monitoring of operational signals across Azure Monitor, App Insights, Akamai, SOA, CommerceTools, Contentstack, Google Analytics for order trend dips, customer feedback signals, error spikes</a:t></a:r></a:p></a:txBody><a:tcPr marL="76200" marR="76200" marT="76200" marB="76200" anchor="ctr"><a:lnL w="9525" cap="flat" cmpd="sng" algn="ctr"><a:noFill/><a:prstDash val="solid"/><a:round/><a:headEnd type="none" w="med" len="med"/><a:tailEnd type="none" w="med" len="med"/></a:lnL><a:lnR w="9525" cap="flat" cmpd="sng" algn="ctr"><a:noFill/><a:prstDash val="solid"/><a:round/><a:headEnd type="none" w="med" len="med"/><a:tailEnd type="none" w="med" len="med"/></a:lnR><a:lnT w="9525" cap="flat" cmpd="sng" algn="ctr"><a:noFill/><a:prstDash val="solid"/><a:round/><a:headEnd type="none" w="med" len="med"/><a:tailEnd type="none" w="med" len="med"/></a:lnT><a:lnB w="9525" cap="flat" cmpd="sng" algn="ctr"><a:noFill/><a:prstDash val="solid"/><a:round/><a:headEnd type="none" w="med" len="med"/><a:tailEnd type="none" w="med" len="med"/></a:lnB><a:lnTlToBr w="12700" cmpd="sng"><a:noFill/><a:prstDash val="solid"/></a:lnTlToBr><a:lnBlToTr w="12700" cmpd="sng"><a:noFill/><a:prstDash val="solid"/></a:lnBlToTr><a:noFill/></a:tcPr></a:tc><a:tc><a:txBody><a:bodyPr/><a:lstStyle/><a:p><a:pPr algn="ctr" fontAlgn="t"><a:buNone/></a:pPr><a:r><a:rPr lang="en-US" sz="1050" b="0" i="0" u="none" strike="noStrike" kern="1200" baseline="0"><a:solidFill><a:srgbClr val="000000"/></a:solidFill><a:effectLst/><a:latin typeface="+mn-lt"/><a:ea typeface="+mn-ea"/><a:cs typeface="+mn-cs"/></a:rPr><a:t>Observability Insights </a:t></a:r></a:p><a:p><a:pPr algn="ctr" fontAlgn="t"><a:buNone/></a:pPr><a:r><a:rPr lang="en-US" sz="1050" b="0" i="0" u="none" strike="noStrike" kern="1200" baseline="0"><a:solidFill><a:srgbClr val="000000"/></a:solidFill><a:effectLst/><a:latin typeface="+mn-lt"/><a:ea typeface="+mn-ea"/><a:cs typeface="+mn-cs"/></a:rPr><a:t>Super Agent</a:t></a:r></a:p></a:txBody><a:tcPr marL="76200" marR="76200" marT="76200" marB="76200" anchor="ctr"><a:lnL w="9525" cap="flat" cmpd="sng" algn="ctr"><a:noFill/><a:prstDash val="solid"/><a:round/><a:headEnd type="none" w="med" len="med"/><a:tailEnd type="none" w="med" len="med"/></a:lnL><a:lnR w="9524"><a:noFill/></a:lnR><a:lnT w="9524" cap="flat" cmpd="sng" algn="ctr"><a:noFill/><a:prstDash val="solid"/><a:round/><a:headEnd type="none" w="med" len="med"/><a:tailEnd type="none" w="med" len="med"/></a:lnT><a:lnB w="9524" cap="flat" cmpd="sng" algn="ctr"><a:noFill/><a:prstDash val="solid"/><a:round/><a:headEnd type="none" w="med" len="med"/><a:tailEnd type="none" w="med" len="med"/></a:lnB><a:lnTlToBr w="12700" cmpd="sng"><a:noFill/><a:prstDash val="solid"/></a:lnTlToBr><a:lnBlToTr w="12700" cmpd="sng"><a:noFill/><a:prstDash val="solid"/></a:lnBlToTr><a:noFill/></a:tcPr></a:tc><a:tc><a:txBody><a:bodyPr/><a:lstStyle/><a:p><a:pPr><a:lnSpc><a:spcPts val="1100"/></a:lnSpc></a:pPr><a:r><a:rPr sz="800" b="1"><a:solidFill><a:srgbClr val="383838"/></a:solidFill><a:latin typeface="GT Walsheim Bold"/></a:rPr><a:t>Log Analysis Agent — </a:t></a:r><a:r><a:rPr sz="800" b="0"><a:solidFill><a:srgbClr val="484848"/></a:solidFill><a:latin typeface="GT Walsheim Light"/></a:rPr><a:t>multi-source log mining (App Insights / Azure Monitor)</a:t></a:r></a:p><a:p><a:pPr><a:lnSpc><a:spcPts val="1100"/></a:lnSpc></a:pPr><a:r><a:rPr sz="800" b="1"><a:solidFill><a:srgbClr val="383838"/></a:solidFill><a:latin typeface="GT Walsheim Bold"/></a:rPr><a:t>Metric Correlation Agent — </a:t></a:r><a:r><a:rPr sz="800" b="0"><a:solidFill><a:srgbClr val="484848"/></a:solidFill><a:latin typeface="GT Walsheim Light"/></a:rPr><a:t>time-series anomaly across CDN / commerce</a:t></a:r></a:p><a:p><a:pPr><a:lnSpc><a:spcPts val="1100"/></a:lnSpc></a:pPr><a:r><a:rPr sz="800" b="1"><a:solidFill><a:srgbClr val="383838"/></a:solidFill><a:latin typeface="GT Walsheim Bold"/></a:rPr><a:t>Signal Fusion Agent — </a:t></a:r><a:r><a:rPr sz="800" b="0"><a:solidFill><a:srgbClr val="484848"/></a:solidFill><a:latin typeface="GT Walsheim Light"/></a:rPr><a:t>cross-platform correlation &amp; noise reduction</a:t></a:r></a:p><a:p><a:pPr><a:lnSpc><a:spcPts val="1100"/></a:lnSpc></a:pPr><a:r><a:rPr sz="800" b="1"><a:solidFill><a:srgbClr val="383838"/></a:solidFill><a:latin typeface="GT Walsheim Bold"/></a:rPr><a:t>Trend &amp; Feedback Agent — </a:t></a:r><a:r><a:rPr sz="800" b="0"><a:solidFill><a:srgbClr val="484848"/></a:solidFill><a:latin typeface="GT Walsheim Light"/></a:rPr><a:t>order trends &amp; customer feedback signals</a:t></a:r></a:p><a:p><a:pPr><a:lnSpc><a:spcPts val="1100"/></a:lnSpc></a:pPr><a:r><a:rPr sz="800" b="1"><a:solidFill><a:srgbClr val="5BA4AF"/></a:solidFill><a:latin typeface="GT Walsheim Bold"/></a:rPr><a:t>Scoring Agent — </a:t></a:r><a:r><a:rPr sz="800" b="0"><a:solidFill><a:srgbClr val="484848"/></a:solidFill><a:latin typeface="GT Walsheim Light"/></a:rPr><a:t>priority, severity &amp; business impact</a:t></a:r></a:p><a:p><a:pPr><a:lnSpc><a:spcPts val="1100"/></a:lnSpc></a:pPr><a:r><a:rPr sz="800" b="1"><a:solidFill><a:srgbClr val="5BA4AF"/></a:solidFill><a:latin typeface="GT Walsheim Bold"/></a:rPr><a:t>RCA Agent — </a:t></a:r><a:r><a:rPr sz="800" b="0"><a:solidFill><a:srgbClr val="484848"/></a:solidFill><a:latin typeface="GT Walsheim Light"/></a:rPr><a:t>root cause analysis generation</a:t></a:r></a:p><a:p><a:pPr><a:lnSpc><a:spcPts val="1100"/></a:lnSpc></a:pPr><a:r><a:rPr sz="800" b="1"><a:solidFill><a:srgbClr val="5BA4AF"/></a:solidFill><a:latin typeface="GT Walsheim Bold"/></a:rPr><a:t>Ticket Agent — </a:t></a:r><a:r><a:rPr sz="800" b="0"><a:solidFill><a:srgbClr val="484848"/></a:solidFill><a:latin typeface="GT Walsheim Light"/></a:rPr><a:t>Remedy ticket creation</a:t></a:r></a:p><a:p><a:pPr><a:lnSpc><a:spcPts val="1100"/></a:lnSpc></a:pPr><a:r><a:rPr sz="800" b="1"><a:solidFill><a:srgbClr val="5BA4AF"/></a:solidFill><a:latin typeface="GT Walsheim Bold"/></a:rPr><a:t>Knowledge Agent — </a:t></a:r><a:r><a:rPr sz="800" b="0"><a:solidFill><a:srgbClr val="484848"/></a:solidFill><a:latin typeface="GT Walsheim Light"/></a:rPr><a:t>KB update &amp; continuous learning</a:t></a:r></a:p><a:p><a:pPr><a:lnSpc><a:spcPts val="1100"/></a:lnSpc></a:pPr><a:r><a:rPr sz="800" b="1"><a:solidFill><a:srgbClr val="5BA4AF"/></a:solidFill><a:latin typeface="GT Walsheim Bold"/></a:rPr><a:t>Notification Agent — </a:t></a:r><a:r><a:rPr sz="800" b="0"><a:solidFill><a:srgbClr val="484848"/></a:solidFill><a:latin typeface="GT Walsheim Light"/></a:rPr><a:t>Teams, email &amp; xMatters escalation</a:t></a:r></a:p></a:txBody><a:tcPr marL="76200" marR="76200" marT="76200" marB="76200" anchor="ctr"><a:lnL w="9524" cap="flat" cmpd="sng" algn="ctr"><a:noFill/><a:prstDash val="solid"/><a:round/><a:headEnd type="none" w="med" len="med"/><a:tailEnd type="none" w="med" len="med"/></a:lnL><a:lnR w="9524" cap="flat" cmpd="sng" algn="ctr"><a:noFill/><a:prstDash val="solid"/><a:round/><a:headEnd type="none" w="med" len="med"/><a:tailEnd type="none" w="med" len="med"/></a:lnR><a:lnT w="9525" cap="flat" cmpd="sng" algn="ctr"><a:noFill/><a:prstDash val="solid"/><a:round/><a:headEnd type="none" w="med" len="med"/><a:tailEnd type="none" w="med" len="med"/></a:lnT><a:lnB w="9525" cap="flat" cmpd="sng" algn="ctr"><a:noFill/><a:prstDash val="solid"/><a:round/><a:headEnd type="none" w="med" len="med"/><a:tailEnd type="none" w="med" len="med"/></a:lnB><a:lnTlToBr w="12700" cmpd="sng"><a:noFill/><a:prstDash val="solid"/></a:lnTlToBr><a:lnBlToTr w="12700" cmpd="sng"><a:noFill/><a:prstDash val="solid"/></a:lnBlToTr><a:noFill/></a:tcPr></a:tc><a:tc><a:txBody><a:bodyPr/><a:lstStyle/><a:p><a:endParaRPr sz="800" b="0"><a:solidFill><a:srgbClr val="484848"/></a:solidFill><a:latin typeface="GT Walsheim Light"/></a:endParaRPr></a:p></a:txBody><a:tcPr marL="76200" marR="76200" marT="76200" marB="76200" anchor="ctr"><a:lnL w="9524" cap="flat" cmpd="sng" algn="ctr"><a:noFill/><a:prstDash val="solid"/><a:round/><a:headEnd type="none" w="med" len="med"/><a:tailEnd type="none" w="med" len="med"/></a:lnL><a:lnR w="9525" cap="flat" cmpd="sng" algn="ctr"><a:noFill/><a:prstDash val="solid"/><a:round/><a:headEnd type="none" w="med" len="med"/><a:tailEnd type="none" w="med" len="med"/></a:lnR><a:lnT w="9525" cap="flat" cmpd="sng" algn="ctr"><a:noFill/><a:prstDash val="solid"/><a:round/><a:headEnd type="none" w="med" len="med"/><a:tailEnd type="none" w="med" len="med"/></a:lnT><a:lnB w="9525" cap="flat" cmpd="sng" algn="ctr"><a:noFill/><a:prstDash val="solid"/><a:round/><a:headEnd type="none" w="med" len="med"/><a:tailEnd type="none" w="med" len="med"/></a:lnB><a:lnTlToBr w="12700" cmpd="sng"><a:noFill/><a:prstDash val="solid"/></a:lnTlToBr><a:lnBlToTr w="12700" cmpd="sng"><a:noFill/><a:prstDash val="solid"/></a:lnBlToTr><a:noFill/></a:tcPr></a:tc><a:extLst><a:ext uri="{0D108BD9-81ED-4DB2-BD59-A6C34878D82A}"><a16:rowId xmlns:a16="http://schemas.microsoft.com/office/drawing/2014/main" val="2884331946"/></a:ext></a:extLst></a:tr><a:tr h="701143"><a:tc><a:txBody><a:bodyPr/><a:lstStyle/><a:p><a:pPr lvl="0" algn="ctr"><a:lnSpc><a:spcPts val="1425"/></a:lnSpc><a:buNone/></a:pPr><a:r><a:rPr lang="en-US" sz="1100"><a:effectLst/><a:latin typeface="+mn-lt"/></a:rPr><a:t>UC4</a:t></a:r><a:endParaRPr lang="en-US" sz="1600"><a:effectLst/><a:latin typeface="+mn-lt"/></a:endParaRPr></a:p></a:txBody><a:tcPr marL="45720" marR="45720" anchor="ctr"><a:lnL w="9525" cap="flat" cmpd="sng" algn="ctr"><a:noFill/><a:prstDash val="solid"/><a:round/><a:headEnd type="none" w="med" len="med"/><a:tailEnd type="none" w="med" len="med"/></a:lnL><a:lnR w="9525" cap="flat" cmpd="sng" algn="ctr"><a:noFill/><a:prstDash val="solid"/><a:round/><a:headEnd type="none" w="med" len="med"/><a:tailEnd type="none" w="med" len="med"/></a:lnR><a:lnT w="9525" cap="flat" cmpd="sng" algn="ctr"><a:noFill/><a:prstDash val="solid"/><a:round/><a:headEnd type="none" w="med" len="med"/><a:tailEnd type="none" w="med" len="med"/></a:lnT><a:lnB w="9525" cap="flat" cmpd="sng" algn="ctr"><a:noFill/><a:prstDash val="solid"/><a:round/><a:headEnd type="none" w="med" len="med"/><a:tailEnd type="none" w="med" len="med"/></a:lnB><a:lnTlToBr w="12700" cmpd="sng"><a:noFill/><a:prstDash val="solid"/></a:lnTlToBr><a:lnBlToTr w="12700" cmpd="sng"><a:noFill/><a:prstDash val="solid"/></a:lnBlToTr><a:solidFill><a:srgbClr val="E8F5F7"/></a:solidFill></a:tcPr></a:tc><a:tc><a:txBody><a:bodyPr/><a:lstStyle/><a:p><a:pPr marL="0" lvl="0" indent="0" algn="ctr"><a:buNone/></a:pPr><a:r><a:rPr lang="en-US" sz="1050" b="0" i="0" u="none" strike="noStrike" baseline="0" noProof="0"><a:solidFill><a:srgbClr val="000000"/></a:solidFill><a:effectLst/><a:latin typeface="+mn-lt"/></a:rPr><a:t>Service Desk Automation for L1 Support</a:t></a:r></a:p></a:txBody><a:tcPr marL="45720" marR="45720" anchor="ctr"><a:lnL w="9525" cap="flat" cmpd="sng" algn="ctr"><a:noFill/><a:prstDash val="solid"/><a:round/><a:headEnd type="none" w="med" len="med"/><a:tailEnd type="none" w="med" len="med"/></a:lnL><a:lnR w="9525" cap="flat" cmpd="sng" algn="ctr"><a:noFill/><a:prstDash val="solid"/><a:round/><a:headEnd type="none" w="med" len="med"/><a:tailEnd type="none" w="med" len="med"/></a:lnR><a:lnT w="9525" cap="flat" cmpd="sng" algn="ctr"><a:noFill/><a:prstDash val="solid"/><a:round/><a:headEnd type="none" w="med" len="med"/><a:tailEnd type="none" w="med" len="med"/></a:lnT><a:lnB w="9525" cap="flat" cmpd="sng" algn="ctr"><a:noFill/><a:prstDash val="solid"/><a:round/><a:headEnd type="none" w="med" len="med"/><a:tailEnd type="none" w="med" len="med"/></a:lnB><a:lnTlToBr w="12700" cmpd="sng"><a:noFill/><a:prstDash val="solid"/></a:lnTlToBr><a:lnBlToTr w="12700" cmpd="sng"><a:noFill/><a:prstDash val="solid"/></a:lnBlToTr><a:solidFill><a:srgbClr val="E8F5F7"/></a:solidFill></a:tcPr></a:tc><a:tc><a:txBody><a:bodyPr/><a:lstStyle/><a:p><a:pPr algn="l" fontAlgn="t"><a:buNone/></a:pPr><a:r><a:rPr lang="en-US" sz="1050" b="0" i="0" u="none" strike="noStrike" kern="1200" baseline="0"><a:solidFill><a:srgbClr val="000000"/></a:solidFill><a:effectLst/><a:latin typeface="+mn-lt"/><a:ea typeface="+mn-ea"/><a:cs typeface="+mn-cs"/></a:rPr><a:t>L1 task automation, password reset, DOB update, CCPA requests, standard customer / account support actions</a:t></a:r></a:p></a:txBody><a:tcPr marL="76200" marR="76200" marT="76200" marB="76200" anchor="ctr"><a:lnL w="9525" cap="flat" cmpd="sng" algn="ctr"><a:noFill/><a:prstDash val="solid"/><a:round/><a:headEnd type="none" w="med" len="med"/><a:tailEnd type="none" w="med" len="med"/></a:lnL><a:lnR w="9525" cap="flat" cmpd="sng" algn="ctr"><a:noFill/><a:prstDash val="solid"/><a:round/><a:headEnd type="none" w="med" len="med"/><a:tailEnd type="none" w="med" len="med"/></a:lnR><a:lnT w="9525" cap="flat" cmpd="sng" algn="ctr"><a:noFill/><a:prstDash val="solid"/><a:round/><a:headEnd type="none" w="med" len="med"/><a:tailEnd type="none" w="med" len="med"/></a:lnT><a:lnB w="9525" cap="flat" cmpd="sng" algn="ctr"><a:noFill/><a:prstDash val="solid"/><a:round/><a:headEnd type="none" w="med" len="med"/><a:tailEnd type="none" w="med" len="med"/></a:lnB><a:lnTlToBr w="12700" cmpd="sng"><a:noFill/><a:prstDash val="solid"/></a:lnTlToBr><a:lnBlToTr w="12700" cmpd="sng"><a:noFill/><a:prstDash val="solid"/></a:lnBlToTr><a:solidFill><a:srgbClr val="E8F5F7"/></a:solidFill></a:tcPr></a:tc><a:tc><a:txBody><a:bodyPr/><a:lstStyle/><a:p><a:pPr algn="ctr" fontAlgn="t"><a:buNone/></a:pPr><a:r><a:rPr lang="en-US" sz="1050" b="0" i="0" u="none" strike="noStrike" kern="1200" baseline="0"><a:solidFill><a:srgbClr val="000000"/></a:solidFill><a:effectLst/><a:latin typeface="+mn-lt"/><a:ea typeface="+mn-ea"/><a:cs typeface="+mn-cs"/></a:rPr><a:t>L1 Automation </a:t></a:r></a:p><a:p><a:pPr algn="ctr" fontAlgn="t"><a:buNone/></a:pPr><a:r><a:rPr lang="en-US" sz="1050" b="0" i="0" u="none" strike="noStrike" kern="1200" baseline="0"><a:solidFill><a:srgbClr val="000000"/></a:solidFill><a:effectLst/><a:latin typeface="+mn-lt"/><a:ea typeface="+mn-ea"/><a:cs typeface="+mn-cs"/></a:rPr><a:t>Super Agent</a:t></a:r></a:p></a:txBody><a:tcPr marL="76200" marR="76200" marT="76200" marB="76200" anchor="ctr"><a:lnL w="9525" cap="flat" cmpd="sng" algn="ctr"><a:noFill/><a:prstDash val="solid"/><a:round/><a:headEnd type="none" w="med" len="med"/><a:tailEnd type="none" w="med" len="med"/></a:lnL><a:lnR w="9524"><a:noFill/></a:lnR><a:lnT w="9524" cap="flat" cmpd="sng" algn="ctr"><a:noFill/><a:prstDash val="solid"/><a:round/><a:headEnd type="none" w="med" len="med"/><a:tailEnd type="none" w="med" len="med"/></a:lnT><a:lnB w="9524"><a:noFill/></a:lnB><a:lnTlToBr w="12700" cmpd="sng"><a:noFill/><a:prstDash val="solid"/></a:lnTlToBr><a:lnBlToTr w="12700" cmpd="sng"><a:noFill/><a:prstDash val="solid"/></a:lnBlToTr><a:solidFill><a:srgbClr val="E8F5F7"/></a:solidFill></a:tcPr></a:tc><a:tc><a:txBody><a:bodyPr/><a:lstStyle/><a:p><a:pPr><a:lnSpc><a:spcPts val="1100"/></a:lnSpc></a:pPr><a:r><a:rPr sz="800" b="1"><a:solidFill><a:srgbClr val="383838"/></a:solidFill><a:latin typeface="GT Walsheim Bold"/></a:rPr><a:t>Identity Verification Agent — </a:t></a:r><a:r><a:rPr sz="800" b="0"><a:solidFill><a:srgbClr val="484848"/></a:solidFill><a:latin typeface="GT Walsheim Light"/></a:rPr><a:t>auth + KYC checks</a:t></a:r></a:p><a:p><a:pPr><a:lnSpc><a:spcPts val="1100"/></a:lnSpc></a:pPr><a:r><a:rPr sz="800" b="1"><a:solidFill><a:srgbClr val="383838"/></a:solidFill><a:latin typeface="GT Walsheim Bold"/></a:rPr><a:t>Account Update Agent — </a:t></a:r><a:r><a:rPr sz="800" b="0"><a:solidFill><a:srgbClr val="484848"/></a:solidFill><a:latin typeface="GT Walsheim Light"/></a:rPr><a:t>password reset, DOB, profile changes</a:t></a:r></a:p><a:p><a:pPr><a:lnSpc><a:spcPts val="1100"/></a:lnSpc></a:pPr><a:r><a:rPr sz="800" b="1"><a:solidFill><a:srgbClr val="383838"/></a:solidFill><a:latin typeface="GT Walsheim Bold"/></a:rPr><a:t>Compliance Request Agent — </a:t></a:r><a:r><a:rPr sz="800" b="0"><a:solidFill><a:srgbClr val="484848"/></a:solidFill><a:latin typeface="GT Walsheim Light"/></a:rPr><a:t>CCPA / GDPR / DSAR workflow</a:t></a:r></a:p><a:p><a:pPr><a:lnSpc><a:spcPts val="1100"/></a:lnSpc></a:pPr><a:r><a:rPr sz="800" b="1"><a:solidFill><a:srgbClr val="383838"/></a:solidFill><a:latin typeface="GT Walsheim Bold"/></a:rPr><a:t>Audit &amp; Notification Agent — </a:t></a:r><a:r><a:rPr sz="800" b="0"><a:solidFill><a:srgbClr val="484848"/></a:solidFill><a:latin typeface="GT Walsheim Light"/></a:rPr><a:t>action logging + customer comms</a:t></a:r></a:p></a:txBody><a:tcPr marL="76200" marR="76200" marT="76200" marB="76200" anchor="ctr"><a:lnL w="9524" cap="flat" cmpd="sng" algn="ctr"><a:noFill/><a:prstDash val="solid"/><a:round/><a:headEnd type="none" w="med" len="med"/><a:tailEnd type="none" w="med" len="med"/></a:lnL><a:lnR w="9524" cap="flat" cmpd="sng" algn="ctr"><a:noFill/><a:prstDash val="solid"/><a:round/><a:headEnd type="none" w="med" len="med"/><a:tailEnd type="none" w="med" len="med"/></a:lnR><a:lnT w="9525" cap="flat" cmpd="sng" algn="ctr"><a:noFill/><a:prstDash val="solid"/><a:round/><a:headEnd type="none" w="med" len="med"/><a:tailEnd type="none" w="med" len="med"/></a:lnT><a:lnB w="9525" cap="flat" cmpd="sng" algn="ctr"><a:noFill/><a:prstDash val="solid"/><a:round/><a:headEnd type="none" w="med" len="med"/><a:tailEnd type="none" w="med" len="med"/></a:lnB><a:lnTlToBr w="12700" cmpd="sng"><a:noFill/><a:prstDash val="solid"/></a:lnTlToBr><a:lnBlToTr w="12700" cmpd="sng"><a:noFill/><a:prstDash val="solid"/></a:lnBlToTr><a:solidFill><a:srgbClr val="E8F5F7"/></a:solidFill></a:tcPr></a:tc><a:tc><a:txBody><a:bodyPr/><a:lstStyle/><a:p><a:endParaRPr sz="800" b="0" dirty="0"><a:solidFill><a:srgbClr val="484848"/></a:solidFill><a:latin typeface="GT Walsheim Light"/></a:endParaRPr></a:p></a:txBody><a:tcPr marL="76200" marR="76200" marT="76200" marB="76200" anchor="ctr"><a:lnL w="9524" cap="flat" cmpd="sng" algn="ctr"><a:noFill/><a:prstDash val="solid"/><a:round/><a:headEnd type="none" w="med" len="med"/><a:tailEnd type="none" w="med" len="med"/></a:lnL><a:lnR w="9525" cap="flat" cmpd="sng" algn="ctr"><a:noFill/><a:prstDash val="solid"/><a:round/><a:headEnd type="none" w="med" len="med"/><a:tailEnd type="none" w="med" len="med"/></a:lnR><a:lnT w="9525" cap="flat" cmpd="sng" algn="ctr"><a:noFill/><a:prstDash val="solid"/><a:round/><a:headEnd type="none" w="med" len="med"/><a:tailEnd type="none" w="med" len="med"/></a:lnT><a:lnB w="9525" cap="flat" cmpd="sng" algn="ctr"><a:noFill/><a:prstDash val="solid"/><a:round/><a:headEnd type="none" w="med" len="med"/><a:tailEnd type="none" w="med" len="med"/></a:lnB><a:lnTlToBr w="12700" cmpd="sng"><a:noFill/><a:prstDash val="solid"/></a:lnTlToBr><a:lnBlToTr w="12700" cmpd="sng"><a:noFill/><a:prstDash val="solid"/></a:lnBlToTr><a:solidFill><a:srgbClr val="E8F5F7"/></a:solidFill></a:tcPr></a:tc><a:extLst><a:ext uri="{0D108BD9-81ED-4DB2-BD59-A6C34878D82A}"><a16:rowId xmlns:a16="http://schemas.microsoft.com/office/drawing/2014/main" val="762675087"/></a:ext></a:extLst></a:tr></a:tbl></a:graphicData></a:graphic></p:graphicFrame><p:sp><p:nvSpPr><p:cNvPr id="2" name="TextBox 1"><a:extLst><a:ext uri="{FF2B5EF4-FFF2-40B4-BE49-F238E27FC236}"><a16:creationId xmlns:a16="http://schemas.microsoft.com/office/drawing/2014/main" id="{CFE4B201-0A97-CA81-807D-1CCA4AB9AAD2}"/></a:ext></a:extLst></p:cNvPr><p:cNvSpPr txBox="1"/><p:nvPr/></p:nvSpPr><p:spPr><a:xfrm><a:off x="0" y="990852"/><a:ext cx="12192000" cy="523220"/></a:xfrm><a:prstGeom prst="rect"><a:avLst/></a:prstGeom><a:solidFill><a:srgbClr val="A9D9E1"/></a:solidFill><a:ln><a:noFill/></a:ln></p:spPr><p:txBody><a:bodyPr wrap="square"><a:spAutoFit/></a:bodyPr><a:lstStyle/><a:p><a:pPr marL="0" marR="0" lvl="0" indent="0" algn="ctr" defTabSz="914400" rtl="0" eaLnBrk="1" fontAlgn="auto" latinLnBrk="0" hangingPunct="1"><a:lnSpc><a:spcPct val="100000"/></a:lnSpc><a:spcBef><a:spcPts val="0"/></a:spcBef><a:spcAft><a:spcPts val="0"/></a:spcAft><a:buClrTx/><a:buSzTx/><a:buFontTx/><a:buNone/><a:tabLst/><a:defRPr/></a:pPr><a:r><a:rPr kumimoji="0" lang="en-US" sz="1400" b="0" i="0" u="none" strike="noStrike" kern="1200" cap="none" spc="0" normalizeH="0" baseline="0" noProof="0"><a:ln><a:noFill/></a:ln><a:solidFill><a:srgbClr val="000000"><a:lumMod val="75000"/><a:lumOff val="25000"/></a:srgbClr></a:solidFill><a:effectLst/><a:uLnTx/><a:uFillTx/><a:latin typeface="GT Walsheim Medium"/><a:ea typeface="+mn-ea"/><a:cs typeface="+mn-cs"/></a:rPr><a:t>Below are a few high-value IntelliOps use cases that are commonly prioritized, </a:t></a:r></a:p><a:p><a:pPr marL="0" marR="0" lvl="0" indent="0" algn="ctr" defTabSz="914400" rtl="0" eaLnBrk="1" fontAlgn="auto" latinLnBrk="0" hangingPunct="1"><a:lnSpc><a:spcPct val="100000"/></a:lnSpc><a:spcBef><a:spcPts val="0"/></a:spcBef><a:spcAft><a:spcPts val="0"/></a:spcAft><a:buClrTx/><a:buSzTx/><a:buFontTx/><a:buNone/><a:tabLst/><a:defRPr/></a:pPr><a:r><a:rPr kumimoji="0" lang="en-US" sz="1400" b="0" i="0" u="none" strike="noStrike" kern="1200" cap="none" spc="0" normalizeH="0" baseline="0" noProof="0"><a:ln><a:noFill/></a:ln><a:solidFill><a:srgbClr val="000000"><a:lumMod val="75000"/><a:lumOff val="25000"/></a:srgbClr></a:solidFill><a:effectLst/><a:uLnTx/><a:uFillTx/><a:latin typeface="GT Walsheim Medium"/><a:ea typeface="+mn-ea"/><a:cs typeface="+mn-cs"/></a:rPr><a:t>but the broader set is client-specific and can be extended based on business needs and operating model.</a:t></a:r></a:p></p:txBody></p:sp><p:sp><p:nvSpPr><p:cNvPr id="3" name="Slide Number Placeholder 3"><a:extLst><a:ext uri="{FF2B5EF4-FFF2-40B4-BE49-F238E27FC236}"><a16:creationId xmlns:a16="http://schemas.microsoft.com/office/drawing/2014/main" id="{BD9467E5-15AD-7D26-D1AB-AE3C3DC108D7}"/></a:ext></a:extLst></p:cNvPr><p:cNvSpPr txBox="1"><a:spLocks/></p:cNvSpPr><p:nvPr/></p:nvSpPr><p:spPr><a:xfrm><a:off x="9230864" y="6545298"/><a:ext cx="2743200" cy="254784"/></a:xfrm><a:prstGeom prst="rect"><a:avLst/></a:prstGeom></p:spPr><p:txBody><a:bodyPr/><a:lstStyle><a:defPPr><a:defRPr lang="en-US"/></a:defPPr><a:lvl1pPr marL="0" algn="r" defTabSz="914400" rtl="0" eaLnBrk="1" latinLnBrk="0" hangingPunct="1"><a:defRPr sz="800" b="0" i="0" kern="1200"><a:solidFill><a:schemeClr val="bg1"><a:lumMod val="65000"/></a:schemeClr></a:solidFill><a:latin typeface="GT Walsheim Light" pitchFamily="2" charset="77"/><a:ea typeface="+mn-ea"/><a:cs typeface="+mn-cs"/></a:defRPr></a:lvl1pPr><a:lvl2pPr marL="457200" algn="l" defTabSz="914400" rtl="0" eaLnBrk="1" latinLnBrk="0" hangingPunct="1"><a:defRPr sz="1800" kern="1200"><a:solidFill><a:schemeClr val="tx1"/></a:solidFill><a:latin typeface="+mn-lt"/><a:ea typeface="+mn-ea"/><a:cs typeface="+mn-cs"/></a:defRPr></a:lvl2pPr><a:lvl3pPr marL="914400" algn="l" defTabSz="914400" rtl="0" eaLnBrk="1" latinLnBrk="0" hangingPunct="1"><a:defRPr sz="1800" kern="1200"><a:solidFill><a:schemeClr val="tx1"/></a:solidFill><a:latin typeface="+mn-lt"/><a:ea typeface="+mn-ea"/><a:cs typeface="+mn-cs"/></a:defRPr></a:lvl3pPr><a:lvl4pPr marL="1371600" algn="l" defTabSz="914400" rtl="0" eaLnBrk="1" latinLnBrk="0" hangingPunct="1"><a:defRPr sz="1800" kern="1200"><a:solidFill><a:schemeClr val="tx1"/></a:solidFill><a:latin typeface="+mn-lt"/><a:ea typeface="+mn-ea"/><a:cs typeface="+mn-cs"/></a:defRPr></a:lvl4pPr><a:lvl5pPr marL="1828800" algn="l" defTabSz="914400" rtl="0" eaLnBrk="1" latinLnBrk="0" hangingPunct="1"><a:defRPr sz="1800" kern="1200"><a:solidFill><a:schemeClr val="tx1"/></a:solidFill><a:latin typeface="+mn-lt"/><a:ea typeface="+mn-ea"/><a:cs typeface="+mn-cs"/></a:defRPr></a:lvl5pPr><a:lvl6pPr marL="2286000" algn="l" defTabSz="914400" rtl="0" eaLnBrk="1" latinLnBrk="0" hangingPunct="1"><a:defRPr sz="1800" kern="1200"><a:solidFill><a:schemeClr val="tx1"/></a:solidFill><a:latin typeface="+mn-lt"/><a:ea typeface="+mn-ea"/><a:cs typeface="+mn-cs"/></a:defRPr></a:lvl6pPr><a:lvl7pPr marL="2743200" algn="l" defTabSz="914400" rtl="0" eaLnBrk="1" latinLnBrk="0" hangingPunct="1"><a:defRPr sz="1800" kern="1200"><a:solidFill><a:schemeClr val="tx1"/></a:solidFill><a:latin typeface="+mn-lt"/><a:ea typeface="+mn-ea"/><a:cs typeface="+mn-cs"/></a:defRPr></a:lvl7pPr><a:lvl8pPr marL="3200400" algn="l" defTabSz="914400" rtl="0" eaLnBrk="1" latinLnBrk="0" hangingPunct="1"><a:defRPr sz="1800" kern="1200"><a:solidFill><a:schemeClr val="tx1"/></a:solidFill><a:latin typeface="+mn-lt"/><a:ea typeface="+mn-ea"/><a:cs typeface="+mn-cs"/></a:defRPr></a:lvl8pPr><a:lvl9pPr marL="3657600" algn="l" defTabSz="914400" rtl="0" eaLnBrk="1" latinLnBrk="0" hangingPunct="1"><a:defRPr sz="1800" kern="1200"><a:solidFill><a:schemeClr val="tx1"/></a:solidFill><a:latin typeface="+mn-lt"/><a:ea typeface="+mn-ea"/><a:cs typeface="+mn-cs"/></a:defRPr></a:lvl9pPr></a:lstStyle><a:p><a:pPr marL="0" marR="0" lvl="0" indent="0" algn="r" defTabSz="914400" rtl="0" eaLnBrk="1" fontAlgn="auto" latinLnBrk="0" hangingPunct="1"><a:lnSpc><a:spcPct val="100000"/></a:lnSpc><a:spcBef><a:spcPts val="0"/></a:spcBef><a:spcAft><a:spcPts val="0"/></a:spcAft><a:buClrTx/><a:buSzTx/><a:buFontTx/><a:buNone/><a:tabLst/><a:defRPr/></a:pPr><a:fld id="{48DB7AE5-2463-B04D-8F6B-B32EFABAF08E}" type="slidenum"><a:rPr kumimoji="0" lang="en-US" sz="800" b="0" i="0" u="none" strike="noStrike" kern="1200" cap="none" spc="0" normalizeH="0" baseline="0" noProof="0" smtClean="0"><a:ln><a:noFill/></a:ln><a:solidFill><a:prstClr val="white"><a:lumMod val="65000"/></a:prstClr></a:solidFill><a:effectLst/><a:uLnTx/><a:uFillTx/><a:latin typeface="GT Walsheim Light" pitchFamily="2" charset="77"/><a:ea typeface="+mn-ea"/><a:cs typeface="+mn-cs"/><a:sym typeface="Arial"/></a:rPr><a:pPr marL="0" marR="0" lvl="0" indent="0" algn="r" defTabSz="914400" rtl="0" eaLnBrk="1" fontAlgn="auto" latinLnBrk="0" hangingPunct="1"><a:lnSpc><a:spcPct val="100000"/></a:lnSpc><a:spcBef><a:spcPts val="0"/></a:spcBef><a:spcAft><a:spcPts val="0"/></a:spcAft><a:buClrTx/><a:buSzTx/><a:buFontTx/><a:buNone/><a:tabLst/><a:defRPr/></a:pPr><a:t>21</a:t></a:fld><a:endParaRPr kumimoji="0" lang="en-US" sz="800" b="0" i="0" u="none" strike="noStrike" kern="1200" cap="none" spc="0" normalizeH="0" baseline="0" noProof="0"><a:ln><a:noFill/></a:ln><a:solidFill><a:prstClr val="white"><a:lumMod val="65000"/></a:prstClr></a:solidFill><a:effectLst/><a:uLnTx/><a:uFillTx/><a:latin typeface="GT Walsheim Light" pitchFamily="2" charset="77"/><a:ea typeface="+mn-ea"/><a:cs typeface="+mn-cs"/><a:sym typeface="Arial"/></a:endParaRPr></a:p></p:txBody></p:sp><p:sp><p:nvSpPr><p:cNvPr id="4" name="Shape 23"><a:hlinkClick r:id="rId4" action="ppaction://hlinksldjump"/><a:extLst><a:ext uri="{FF2B5EF4-FFF2-40B4-BE49-F238E27FC236}"><a16:creationId xmlns:a16="http://schemas.microsoft.com/office/drawing/2014/main" id="{4ADF956D-472C-9773-8048-7915727F4EBF}"/></a:ext></a:extLst></p:cNvPr><p:cNvSpPr/><p:nvPr/></p:nvSpPr><p:spPr><a:xfrm><a:off x="10603072" y="2386271"/><a:ext cx="1101892" cy="336890"/></a:xfrm><a:prstGeom prst="roundRect"><a:avLst/></a:prstGeom><a:solidFill><a:schemeClr val="accent4"/></a:solidFill><a:ln w="6350"><a:solidFill><a:srgbClr val="D9D9D9"/></a:solidFill><a:prstDash val="solid"/></a:ln><a:effectLst><a:outerShdw blurRad="50800" dist="38100" dir="2700000" algn="tl" rotWithShape="0"><a:prstClr val="black"><a:alpha val="40000"/></a:prstClr></a:outerShdw></a:effectLst><a:scene3d><a:camera prst="orthographicFront"/><a:lightRig rig="threePt" dir="t"/></a:scene3d><a:sp3d><a:bevelT w="12700" h="88900"/><a:bevelB w="12700" h="88900"/></a:sp3d></p:spPr><p:txBody><a:bodyPr anchor="ctr"/><a:lstStyle/><a:p><a:pPr marL="0" marR="0" lvl="0" indent="0" algn="ctr" defTabSz="914400" rtl="0" eaLnBrk="1" fontAlgn="auto" latinLnBrk="0" hangingPunct="1"><a:lnSpc><a:spcPct val="100000"/></a:lnSpc><a:spcBef><a:spcPts val="0"/></a:spcBef><a:spcAft><a:spcPts val="0"/></a:spcAft><a:buClrTx/><a:buSzTx/><a:buFontTx/><a:buNone/><a:tabLst/><a:defRPr/></a:pPr><a:r><a:rPr kumimoji="0" lang="en-US" sz="1100" b="1" i="0" u="none" strike="noStrike" kern="1200" cap="none" spc="0" normalizeH="0" baseline="0" noProof="0"><a:ln><a:noFill/></a:ln><a:solidFill><a:srgbClr val="000000"/></a:solidFill><a:effectLst/><a:uLnTx/><a:uFillTx/><a:latin typeface="GT Walsheim Light"/><a:ea typeface="+mn-ea"/><a:cs typeface="+mn-cs"/></a:rPr><a:t>▶  Deep Dive </a:t></a:r></a:p></p:txBody></p:sp><p:sp><p:nvSpPr><p:cNvPr id="5" name="Shape 23"><a:hlinkClick r:id="rId5" action="ppaction://hlinksldjump"/><a:extLst><a:ext uri="{FF2B5EF4-FFF2-40B4-BE49-F238E27FC236}"><a16:creationId xmlns:a16="http://schemas.microsoft.com/office/drawing/2014/main" id="{7CAF892E-B036-8446-38C8-39F51A44EA0B}"/></a:ext></a:extLst></p:cNvPr><p:cNvSpPr/><p:nvPr/></p:nvSpPr><p:spPr><a:xfrm><a:off x="10603072" y="3773934"/><a:ext cx="1101892" cy="336890"/></a:xfrm><a:prstGeom prst="roundRect"><a:avLst/></a:prstGeom><a:solidFill><a:schemeClr val="accent4"/></a:solidFill><a:ln w="6350"><a:solidFill><a:srgbClr val="D9D9D9"/></a:solidFill><a:prstDash val="solid"/></a:ln><a:effectLst><a:outerShdw blurRad="50800" dist="38100" dir="2700000" algn="tl" rotWithShape="0"><a:prstClr val="black"><a:alpha val="40000"/></a:prstClr></a:outerShdw></a:effectLst><a:scene3d><a:camera prst="orthographicFront"/><a:lightRig rig="threePt" dir="t"/></a:scene3d><a:sp3d><a:bevelT w="12700" h="88900"/><a:bevelB w="12700" h="88900"/></a:sp3d></p:spPr><p:txBody><a:bodyPr anchor="ctr"/><a:lstStyle/><a:p><a:pPr marL="0" marR="0" lvl="0" indent="0" algn="ctr" defTabSz="914400" rtl="0" eaLnBrk="1" fontAlgn="auto" latinLnBrk="0" hangingPunct="1"><a:lnSpc><a:spcPct val="100000"/></a:lnSpc><a:spcBef><a:spcPts val="0"/></a:spcBef><a:spcAft><a:spcPts val="0"/></a:spcAft><a:buClrTx/><a:buSzTx/><a:buFontTx/><a:buNone/><a:tabLst/><a:defRPr/></a:pPr><a:r><a:rPr kumimoji="0" lang="en-US" sz="1100" b="1" i="0" u="none" strike="noStrike" kern="1200" cap="none" spc="0" normalizeH="0" baseline="0" noProof="0"><a:ln><a:noFill/></a:ln><a:solidFill><a:srgbClr val="000000"/></a:solidFill><a:effectLst/><a:uLnTx/><a:uFillTx/><a:latin typeface="GT Walsheim Light"/><a:ea typeface="+mn-ea"/><a:cs typeface="+mn-cs"/></a:rPr><a:t>▶  Deep Dive </a:t></a:r></a:p></p:txBody></p:sp><p:sp><p:nvSpPr><p:cNvPr id="6" name="Shape 23"><a:hlinkClick r:id="rId6" action="ppaction://hlinksldjump"/><a:extLst><a:ext uri="{FF2B5EF4-FFF2-40B4-BE49-F238E27FC236}"><a16:creationId xmlns:a16="http://schemas.microsoft.com/office/drawing/2014/main" id="{3E5A18BD-80E6-2E1D-A454-1191176CBA05}"/></a:ext></a:extLst></p:cNvPr><p:cNvSpPr/><p:nvPr/></p:nvSpPr><p:spPr><a:xfrm><a:off x="10613926" y="5059097"/><a:ext cx="1101892" cy="336890"/></a:xfrm><a:prstGeom prst="roundRect"><a:avLst/></a:prstGeom><a:solidFill><a:schemeClr val="accent4"/></a:solidFill><a:ln w="6350"><a:solidFill><a:srgbClr val="D9D9D9"/></a:solidFill><a:prstDash val="solid"/></a:ln><a:effectLst><a:outerShdw blurRad="50800" dist="38100" dir="2700000" algn="tl" rotWithShape="0"><a:prstClr val="black"><a:alpha val="40000"/></a:prstClr></a:outerShdw></a:effectLst><a:scene3d><a:camera prst="orthographicFront"/><a:lightRig rig="threePt" dir="t"/></a:scene3d><a:sp3d><a:bevelT w="12700" h="88900"/><a:bevelB w="12700" h="88900"/></a:sp3d></p:spPr><p:txBody><a:bodyPr anchor="ctr"/><a:lstStyle/><a:p><a:pPr marL="0" marR="0" lvl="0" indent="0" algn="ctr" defTabSz="914400" rtl="0" eaLnBrk="1" fontAlgn="auto" latinLnBrk="0" hangingPunct="1"><a:lnSpc><a:spcPct val="100000"/></a:lnSpc><a:spcBef><a:spcPts val="0"/></a:spcBef><a:spcAft><a:spcPts val="0"/></a:spcAft><a:buClrTx/><a:buSzTx/><a:buFontTx/><a:buNone/><a:tabLst/><a:defRPr/></a:pPr><a:r><a:rPr kumimoji="0" lang="en-US" sz="1100" b="1" i="0" u="none" strike="noStrike" kern="1200" cap="none" spc="0" normalizeH="0" baseline="0" noProof="0"><a:ln><a:noFill/></a:ln><a:solidFill><a:srgbClr val="000000"/></a:solidFill><a:effectLst/><a:uLnTx/><a:uFillTx/><a:latin typeface="GT Walsheim Light"/><a:ea typeface="+mn-ea"/><a:cs typeface="+mn-cs"/></a:rPr><a:t>▶  Deep Dive </a:t></a:r></a:p></p:txBody></p:sp><p:sp><p:nvSpPr><p:cNvPr id="7" name="Shape 23"><a:hlinkClick r:id="rId7" action="ppaction://hlinksldjump"/><a:extLst><a:ext uri="{FF2B5EF4-FFF2-40B4-BE49-F238E27FC236}"><a16:creationId xmlns:a16="http://schemas.microsoft.com/office/drawing/2014/main" id="{827D8C9D-8207-D27A-3792-22780FE296CE}"/></a:ext></a:extLst></p:cNvPr><p:cNvSpPr/><p:nvPr/></p:nvSpPr><p:spPr><a:xfrm><a:off x="10613926" y="6163530"/><a:ext cx="1101892" cy="336890"/></a:xfrm><a:prstGeom prst="roundRect"><a:avLst/></a:prstGeom><a:solidFill><a:schemeClr val="accent4"/></a:solidFill><a:ln w="6350"><a:solidFill><a:srgbClr val="D9D9D9"/></a:solidFill><a:prstDash val="solid"/></a:ln><a:effectLst><a:outerShdw blurRad="50800" dist="38100" dir="2700000" algn="tl" rotWithShape="0"><a:prstClr val="black"><a:alpha val="40000"/></a:prstClr></a:outerShdw></a:effectLst><a:scene3d><a:camera prst="orthographicFront"/><a:lightRig rig="threePt" dir="t"/></a:scene3d><a:sp3d><a:bevelT w="12700" h="88900"/><a:bevelB w="12700" h="88900"/></a:sp3d></p:spPr><p:txBody><a:bodyPr anchor="ctr"/><a:lstStyle/><a:p><a:pPr marL="0" marR="0" lvl="0" indent="0" algn="ctr" defTabSz="914400" rtl="0" eaLnBrk="1" fontAlgn="auto" latinLnBrk="0" hangingPunct="1"><a:lnSpc><a:spcPct val="100000"/></a:lnSpc><a:spcBef><a:spcPts val="0"/></a:spcBef><a:spcAft><a:spcPts val="0"/></a:spcAft><a:buClrTx/><a:buSzTx/><a:buFontTx/><a:buNone/><a:tabLst/><a:defRPr/></a:pPr><a:r><a:rPr kumimoji="0" lang="en-US" sz="1100" b="1" i="0" u="none" strike="noStrike" kern="1200" cap="none" spc="0" normalizeH="0" baseline="0" noProof="0"><a:ln><a:noFill/></a:ln><a:solidFill><a:srgbClr val="000000"/></a:solidFill><a:effectLst/><a:uLnTx/><a:uFillTx/><a:latin typeface="GT Walsheim Light"/><a:ea typeface="+mn-ea"/><a:cs typeface="+mn-cs"/></a:rPr><a:t>▶  Deep Dive </a:t></a:r></a:p></p:txBody></p:sp><p:sp><p:nvSpPr><p:cNvPr id="8" name="Rectangle: Rounded Corners 7"><a:extLst><a:ext uri="{FF2B5EF4-FFF2-40B4-BE49-F238E27FC236}"><a16:creationId xmlns:a16="http://schemas.microsoft.com/office/drawing/2014/main" id="{BC7736DA-2C74-C463-315F-406FACD690B6}"/></a:ext></a:extLst></p:cNvPr><p:cNvSpPr/><p:nvPr/></p:nvSpPr><p:spPr><a:xfrm><a:off x="10752668" y="364776"/><a:ext cx="1160428" cy="261300"/></a:xfrm><a:prstGeom prst="roundRect"><a:avLst><a:gd name="adj" fmla="val 31248"/></a:avLst></a:prstGeom><a:solidFill><a:schemeClr val="bg1"/></a:solidFill><a:ln><a:solidFill><a:schemeClr val="accent5"/></a:solidFill></a:ln></p:spPr><p:style><a:lnRef idx="2"><a:schemeClr val="accent1"><a:shade val="15000"/></a:schemeClr></a:lnRef><a:fillRef idx="1"><a:schemeClr val="accent1"/></a:fillRef><a:effectRef idx="0"><a:schemeClr val="accent1"/></a:effectRef><a:fontRef idx="minor"><a:schemeClr val="lt1"/></a:fontRef></p:style><p:txBody><a:bodyPr rtlCol="0" anchor="ctr"/><a:lstStyle/><a:p><a:pPr marL="0" marR="0" lvl="0" indent="0" algn="ctr" defTabSz="914400" rtl="0" eaLnBrk="1" fontAlgn="auto" latinLnBrk="0" hangingPunct="1"><a:lnSpc><a:spcPct val="100000"/></a:lnSpc><a:spcBef><a:spcPts val="0"/></a:spcBef><a:spcAft><a:spcPts val="0"/></a:spcAft><a:buClrTx/><a:buSzTx/><a:buFontTx/><a:buNone/><a:tabLst/><a:defRPr/></a:pPr><a:r><a:rPr kumimoji="0" lang="en-US" sz="1000" b="0" i="0" u="none" strike="noStrike" kern="1200" cap="none" spc="0" normalizeH="0" baseline="0" noProof="0"><a:ln><a:noFill/></a:ln><a:solidFill><a:srgbClr val="5BA4AF"/></a:solidFill><a:effectLst/><a:uLnTx/><a:uFillTx/><a:latin typeface="GT Walsheim Medium"/><a:ea typeface="+mn-ea"/><a:cs typeface="+mn-cs"/></a:rPr><a:t>Shared Agent</a:t></a:r></a:p></p:txBody></p:sp></p:spTree><p:extLst><p:ext uri="{BB962C8B-B14F-4D97-AF65-F5344CB8AC3E}"><p14:creationId xmlns:p14="http://schemas.microsoft.com/office/powerpoint/2010/main" val="3497830145"/></p:ext></p:extLst></p:cSld><p:clrMapOvr><a:masterClrMapping/></p:clrMapOvr><mc:AlternateContent xmlns:mc="http://schemas.openxmlformats.org/markup-compatibility/2006" xmlns:p14="http://schemas.microsoft.com/office/powerpoint/2010/main"><mc:Choice Requires="p14"><p:transition spd="med" p14:dur="700"><p:fade/></p:transition></mc:Choice><mc:Fallback xmlns=""><p:transition spd="med"><p:fade/></p:transition></mc:Fallback></mc:AlternateContent></p:sld>